[
  {
    "ts": "2026-07-05T22:35:15+00:00",
    "type": "outflow",
    "frxusd": 589.09,
    "asset": "USDC",
    "assetAmount": 589.09,
    "assetValueUSD": 589.09,
    "txUrl": "https://etherscan.io/tx/0xb416ac7f7f10b80db7230d4a8356b4a32beb03d63be56a0698a8ea4855e9797d"
  },
  {
    "ts": "2026-07-05T22:33:25+00:00",
    "type": "outflow",
    "frxusd": 144.41,
    "asset": "USDC",
    "assetAmount": 144.41,
    "assetValueUSD": 144.41,
    "txUrl": "https://etherscan.io/tx/0x14b41e6fe4a117548a00dabaf6a5096b808ef62eb33564ca5dbb7d0618befd85"
  },
  {
    "ts": "2026-07-05T22:30:37+00:00",
    "type": "inflow",
    "frxusd": 975.99,
    "asset": "USDC",
    "assetAmount": 975.99,
    "assetValueUSD": 975.99,
    "txUrl": "https://etherscan.io/tx/0xfd848f3bfe7e9b39683655e3dfa05e9e3f9eb582258909573a491e05e9200a19"
  },
  {
    "ts": "2026-07-05T22:21:02+00:00",
    "type": "inflow",
    "frxusd": 100.31,
    "asset": "USDC",
    "assetAmount": 100.31,
    "assetValueUSD": 100.31,
    "txUrl": "https://etherscan.io/tx/0x5437f81a1f72588ca79363ebe4283a20ee7a9585daa0318eadb460618e03da6d"
  },
  {
    "ts": "2026-07-05T22:10:25+00:00",
    "type": "inflow",
    "frxusd": 405.53,
    "asset": "USDC",
    "assetAmount": 405.53,
    "assetValueUSD": 405.53,
    "txUrl": "https://etherscan.io/tx/0x36a3da09fe8a5cd0a136644fd39cf15a0f70639804d8f106e9748ac6c854403c"
  },
  {
    "ts": "2026-07-05T21:06:01+00:00",
    "type": "outflow",
    "frxusd": 4878.86,
    "asset": "USDC",
    "assetAmount": 4878.86,
    "assetValueUSD": 4878.86,
    "txUrl": "https://etherscan.io/tx/0xdcdd9d71a7f67535c2f33ca2bfad15b377ca062fbe06eadf613ff1bc497070a8"
  },
  {
    "ts": "2026-07-05T21:05:51+00:00",
    "type": "inflow",
    "frxusd": 4804.21,
    "asset": "USDC",
    "assetAmount": 4804.21,
    "assetValueUSD": 4804.21,
    "txUrl": "https://etherscan.io/tx/0xcc360655e7a95fbeb251167aa30aa815838eb6032a9aaa0572d6ef894d28eeae"
  },
  {
    "ts": "2026-07-05T17:42:50+00:00",
    "type": "inflow",
    "frxusd": 54.73,
    "asset": "USDC",
    "assetAmount": 54.73,
    "assetValueUSD": 54.73,
    "txUrl": "https://etherscan.io/tx/0x48782339fe3dabfc9c0c6e0b53b984668df404f9444fb11881af6b4636227b0c"
  },
  {
    "ts": "2026-07-05T17:33:01+00:00",
    "type": "outflow",
    "frxusd": 11814.7,
    "asset": "USDC",
    "assetAmount": 11814.7,
    "assetValueUSD": 11814.7,
    "txUrl": "https://etherscan.io/tx/0x6a75ea85ee36cc49f48230e19579073f102d6a2bb5a419b536fda17c8d4a9495"
  },
  {
    "ts": "2026-07-05T17:32:49+00:00",
    "type": "inflow",
    "frxusd": 11750.0,
    "asset": "USDC",
    "assetAmount": 11750.0,
    "assetValueUSD": 11750.0,
    "txUrl": "https://etherscan.io/tx/0xdb2fd5ffc46826bfc93db6aab2ad6c55ca59a1bbb563160e904a0a218321c002"
  },
  {
    "ts": "2026-07-05T17:29:14+00:00",
    "type": "outflow",
    "frxusd": 234.33,
    "asset": "USDC",
    "assetAmount": 234.33,
    "assetValueUSD": 234.33,
    "txUrl": "https://etherscan.io/tx/0x9e1455b1703f1da433fd0926f28f23fa11aa8586dbbf6d02dd5b4e748ef2951c"
  },
  {
    "ts": "2026-07-05T17:29:13+00:00",
    "type": "inflow",
    "frxusd": 98.23,
    "asset": "USDC",
    "assetAmount": 98.23,
    "assetValueUSD": 98.23,
    "txUrl": "https://etherscan.io/tx/0xd1058221679f5ef32732beeb2cf10f76dec8a5504765fc0d511131e999dc282e"
  },
  {
    "ts": "2026-07-05T16:55:50+00:00",
    "type": "inflow",
    "frxusd": 201.08,
    "asset": "USDC",
    "assetAmount": 201.08,
    "assetValueUSD": 201.08,
    "txUrl": "https://etherscan.io/tx/0x5116d272ffd93785c617540c117d8f0851f8b0330b39b8c8b6aa12a7566be00a"
  },
  {
    "ts": "2026-07-05T16:53:25+00:00",
    "type": "outflow",
    "frxusd": 2154.74,
    "asset": "USDC",
    "assetAmount": 2154.74,
    "assetValueUSD": 2154.74,
    "txUrl": "https://etherscan.io/tx/0x3266739a9de1054d60bfca6d36faea8b06e30ba250d051683fc867821d61e11e"
  },
  {
    "ts": "2026-07-05T16:53:14+00:00",
    "type": "inflow",
    "frxusd": 1494.02,
    "asset": "USDC",
    "assetAmount": 1494.02,
    "assetValueUSD": 1494.02,
    "txUrl": "https://etherscan.io/tx/0x85253a1abe4984298b4e0d6927af600fa18d18a359a8b03d03623104559093b5"
  },
  {
    "ts": "2026-07-05T16:27:37+00:00",
    "type": "outflow",
    "frxusd": 30.18,
    "asset": "USDC",
    "assetAmount": 30.18,
    "assetValueUSD": 30.18,
    "txUrl": "https://etherscan.io/tx/0xad2dda7dbfbbf5617639fa8e6c483317bb7dad4559e7bbbe8357592d3b07dcb6"
  },
  {
    "ts": "2026-07-05T15:56:14+00:00",
    "type": "outflow",
    "frxusd": 6918.24,
    "asset": "USDC",
    "assetAmount": 6918.24,
    "assetValueUSD": 6918.24,
    "txUrl": "https://etherscan.io/tx/0xdba47f43c2436bba00671831cdd04dad632c76abaf0b94e1ee13d361addc62d1"
  },
  {
    "ts": "2026-07-05T15:48:13+00:00",
    "type": "inflow",
    "frxusd": 1500.0,
    "asset": "USDC",
    "assetAmount": 1500.0,
    "assetValueUSD": 1500.0,
    "txUrl": "https://etherscan.io/tx/0x43e48aaf36ad8d8f42226869dd6f5803af61ce78921f940efb345117d10e3798"
  },
  {
    "ts": "2026-07-05T15:41:01+00:00",
    "type": "outflow",
    "frxusd": 38058.99,
    "asset": "USDC",
    "assetAmount": 38058.99,
    "assetValueUSD": 38058.99,
    "txUrl": "https://etherscan.io/tx/0x8353943c0c6e8e1f808ee813fb98467471b3966bd5018c7b0f01dd5ea3d49bee"
  },
  {
    "ts": "2026-07-05T15:40:48+00:00",
    "type": "outflow",
    "frxusd": 43989.78,
    "asset": "USDC",
    "assetAmount": 43989.78,
    "assetValueUSD": 43989.78,
    "txUrl": "https://etherscan.io/tx/0x61106c208c917cff8e4d9d0161e7c5147170b23702027015a9d62c0fe9366adb"
  },
  {
    "ts": "2026-07-05T15:40:01+00:00",
    "type": "outflow",
    "frxusd": 18914.0,
    "asset": "USDC",
    "assetAmount": 18914.0,
    "assetValueUSD": 18914.0,
    "txUrl": "https://etherscan.io/tx/0x30807b12bbc3c864e293b2eeb96a81a1413d0f2c7933564196928e0394d7db53"
  },
  {
    "ts": "2026-07-05T15:39:03+00:00",
    "type": "outflow",
    "frxusd": 392.26,
    "asset": "USDC",
    "assetAmount": 392.26,
    "assetValueUSD": 392.26,
    "txUrl": "https://etherscan.io/tx/0x28d06a69dc94d685ab1bb10009e5810e7a328cb268d5f1dd06388c6380d66248"
  },
  {
    "ts": "2026-07-05T15:27:25+00:00",
    "type": "outflow",
    "frxusd": 4046.91,
    "asset": "USDC",
    "assetAmount": 4046.91,
    "assetValueUSD": 4046.91,
    "txUrl": "https://etherscan.io/tx/0x1086508642d77aaf7bf32fbdb95c2f47539d211eff4b3daefdf20cb5b93d2f90"
  },
  {
    "ts": "2026-07-05T15:12:38+00:00",
    "type": "inflow",
    "frxusd": 788.97,
    "asset": "USDC",
    "assetAmount": 788.97,
    "assetValueUSD": 788.97,
    "txUrl": "https://etherscan.io/tx/0x73efd7968d707128ac22476d87202f3f7a5c63cee68c6e2b624103f9bc1e684b"
  },
  {
    "ts": "2026-07-05T14:42:03+00:00",
    "type": "outflow",
    "frxusd": 116.15,
    "asset": "USDC",
    "assetAmount": 116.15,
    "assetValueUSD": 116.15,
    "txUrl": "https://etherscan.io/tx/0xa8ca3d1725d5ad553b4702922208ec5703a0d074619c321ae1b4746fb86c36cd"
  },
  {
    "ts": "2026-07-05T14:38:12+00:00",
    "type": "inflow",
    "frxusd": 7050.41,
    "asset": "USDC",
    "assetAmount": 7050.41,
    "assetValueUSD": 7050.41,
    "txUrl": "https://etherscan.io/tx/0xdff236707407cc30ede8b970edf9f1f9750524d3d99ccc47e212d1bccf6fb7d7"
  },
  {
    "ts": "2026-07-05T14:37:38+00:00",
    "type": "outflow",
    "frxusd": 24993.45,
    "asset": "USDC",
    "assetAmount": 24993.45,
    "assetValueUSD": 24993.45,
    "txUrl": "https://etherscan.io/tx/0x056fbd632ed0f46149d86cacd3c744ecf0e7ff490b8c2ef64f27a23e280c5ce2"
  },
  {
    "ts": "2026-07-05T14:35:01+00:00",
    "type": "outflow",
    "frxusd": 1110.97,
    "asset": "USDC",
    "assetAmount": 1110.97,
    "assetValueUSD": 1110.97,
    "txUrl": "https://etherscan.io/tx/0xce58922ea9c92309c54610a5eed908e8e221a0100fe7618c0ed954949c2a7c75"
  },
  {
    "ts": "2026-07-05T14:28:25+00:00",
    "type": "inflow",
    "frxusd": 11170.0,
    "asset": "USDC",
    "assetAmount": 11170.0,
    "assetValueUSD": 11170.0,
    "txUrl": "https://etherscan.io/tx/0x704e9775bc86d8c6ca3135462e9ab0f679dc50846a48c6773a1408a4198a228f"
  },
  {
    "ts": "2026-07-05T14:25:25+00:00",
    "type": "inflow",
    "frxusd": 15060.0,
    "asset": "USDC",
    "assetAmount": 15060.0,
    "assetValueUSD": 15060.0,
    "txUrl": "https://etherscan.io/tx/0x818b5f53de143996dc17885538132d5896e1bedf58f58a9387497e3fc33ef6eb"
  },
  {
    "ts": "2026-07-05T14:21:25+00:00",
    "type": "outflow",
    "frxusd": 70000.0,
    "asset": "USDC",
    "assetAmount": 70000.0,
    "assetValueUSD": 70000.0,
    "txUrl": "https://etherscan.io/tx/0x6d15ac10dd8780022abb8575e36403a0d4e061dc675f71e19a9bb7635902956c"
  },
  {
    "ts": "2026-07-05T14:20:01+00:00",
    "type": "outflow",
    "frxusd": 540.1,
    "asset": "USDC",
    "assetAmount": 540.1,
    "assetValueUSD": 540.1,
    "txUrl": "https://etherscan.io/tx/0xdf3facb8100acc6a3f81a287ecf99455c99e39cf00d70c56eb7ec349cc7d30d7"
  },
  {
    "ts": "2026-07-05T14:14:25+00:00",
    "type": "outflow",
    "frxusd": 9.99,
    "asset": "USDC",
    "assetAmount": 9.99,
    "assetValueUSD": 9.99,
    "txUrl": "https://etherscan.io/tx/0x7ddd01153efff273d479067b450da666b97bac8e0069737f5d2694f88a3519dc"
  },
  {
    "ts": "2026-07-05T14:13:13+00:00",
    "type": "inflow",
    "frxusd": 20320.0,
    "asset": "USDC",
    "assetAmount": 20320.0,
    "assetValueUSD": 20320.0,
    "txUrl": "https://etherscan.io/tx/0x2101892c7795e84ff199a83d7c21f8795d8003438d6bf27fe9547caa91bf8972"
  },
  {
    "ts": "2026-07-05T14:08:28+00:00",
    "type": "inflow",
    "frxusd": 27400.0,
    "asset": "USDC",
    "assetAmount": 27400.0,
    "assetValueUSD": 27400.0,
    "txUrl": "https://etherscan.io/tx/0x44359ef838c89203ea8e19d5586c289c57e05338b93b6ce3a86b9993c49f8d39"
  },
  {
    "ts": "2026-07-05T14:06:15+00:00",
    "type": "inflow",
    "frxusd": 36900.0,
    "asset": "USDC",
    "assetAmount": 36900.0,
    "assetValueUSD": 36900.0,
    "txUrl": "https://etherscan.io/tx/0x1b8a826f54fc7517f6ae8c8f367a900adf092e7d11ae276f162b8c9c2dca6acb"
  },
  {
    "ts": "2026-07-05T14:05:13+00:00",
    "type": "outflow",
    "frxusd": 1491.75,
    "asset": "USDC",
    "assetAmount": 1491.75,
    "assetValueUSD": 1491.75,
    "txUrl": "https://etherscan.io/tx/0xc8608d19773048032cd59a674e23b62eaa6c37f1a64cc8f76b89a444dc7b0429"
  },
  {
    "ts": "2026-07-05T14:00:49+00:00",
    "type": "inflow",
    "frxusd": 48968.17,
    "asset": "USDC",
    "assetAmount": 48968.17,
    "assetValueUSD": 48968.17,
    "txUrl": "https://etherscan.io/tx/0x3171e990893d7fc31321c7291e5e2c7cd371155fe7078c5e37cff21b9eaa40bf"
  },
  {
    "ts": "2026-07-05T13:57:14+00:00",
    "type": "inflow",
    "frxusd": 999.32,
    "asset": "USDC",
    "assetAmount": 999.32,
    "assetValueUSD": 999.32,
    "txUrl": "https://etherscan.io/tx/0x355aa9f099c63a304c9e66ac2ce6c5beb5b24142062f624c66102b9ecee838a6"
  },
  {
    "ts": "2026-07-05T13:34:49+00:00",
    "type": "inflow",
    "frxusd": 2136.2,
    "asset": "USDC",
    "assetAmount": 2136.2,
    "assetValueUSD": 2136.2,
    "txUrl": "https://etherscan.io/tx/0xc088008b24a7c938f2504595714290bd2ccaf4daa65d8fa8e32f8beffdbeea69"
  },
  {
    "ts": "2026-07-05T13:33:38+00:00",
    "type": "outflow",
    "frxusd": 2889.68,
    "asset": "USDC",
    "assetAmount": 2889.68,
    "assetValueUSD": 2889.68,
    "txUrl": "https://etherscan.io/tx/0x11e23f57ba4d9162d4a36888d58b7f20dea958821477f7bd6c73d74047e1a2e8"
  },
  {
    "ts": "2026-07-05T13:33:01+00:00",
    "type": "outflow",
    "frxusd": 2140.66,
    "asset": "USDC",
    "assetAmount": 2140.66,
    "assetValueUSD": 2140.66,
    "txUrl": "https://etherscan.io/tx/0xfa1304d1a3165f8cb3b06af436709d62617fef898b513025b8917fda7317d47c"
  },
  {
    "ts": "2026-07-05T13:27:27+00:00",
    "type": "outflow",
    "frxusd": 301.04,
    "asset": "USDC",
    "assetAmount": 301.04,
    "assetValueUSD": 301.04,
    "txUrl": "https://etherscan.io/tx/0x8314f388499be86c710aa6a0c5566c9f8a736cad8c49197c08ab147a773baf91"
  },
  {
    "ts": "2026-07-05T13:26:37+00:00",
    "type": "inflow",
    "frxusd": 645.07,
    "asset": "USDC",
    "assetAmount": 645.07,
    "assetValueUSD": 645.07,
    "txUrl": "https://etherscan.io/tx/0xbe97accef4989eb24fcf33c9f3939641a810acc7f45a8fd197310488d09105b1"
  },
  {
    "ts": "2026-07-05T13:21:01+00:00",
    "type": "outflow",
    "frxusd": 4268.38,
    "asset": "USDC",
    "assetAmount": 4268.38,
    "assetValueUSD": 4268.38,
    "txUrl": "https://etherscan.io/tx/0xa9a21c9af85e35d67d71bb71476b6fc78609319360107cac47b359a8b17671f2"
  },
  {
    "ts": "2026-07-05T13:20:49+00:00",
    "type": "outflow",
    "frxusd": 4383.15,
    "asset": "USDC",
    "assetAmount": 4383.15,
    "assetValueUSD": 4383.15,
    "txUrl": "https://etherscan.io/tx/0x2f65ff0ea187670bc6fc72e4a4c981db3ba02ff5d18e20b7e0af626207c4a9f0"
  },
  {
    "ts": "2026-07-05T13:17:03+00:00",
    "type": "outflow",
    "frxusd": 1132.78,
    "asset": "USDC",
    "assetAmount": 1132.78,
    "assetValueUSD": 1132.78,
    "txUrl": "https://etherscan.io/tx/0x3e7667f846125d2e07684361b555e728fee1e7ca7bb7c5499aa3dfd05dc4e25a"
  },
  {
    "ts": "2026-07-05T13:04:27+00:00",
    "type": "outflow",
    "frxusd": 1900.0,
    "asset": "USDC",
    "assetAmount": 1900.0,
    "assetValueUSD": 1900.0,
    "txUrl": "https://etherscan.io/tx/0x06aeebc86a7b47abf8cc225d32c7e1706dc70f5f1e379f20245ca30f23313606"
  },
  {
    "ts": "2026-07-05T13:03:13+00:00",
    "type": "inflow",
    "frxusd": 80.85,
    "asset": "USDC",
    "assetAmount": 80.85,
    "assetValueUSD": 80.85,
    "txUrl": "https://etherscan.io/tx/0x0c9939c73780965c7dad30aa719829cff92708b75443adb5846af85e6a186a5f"
  },
  {
    "ts": "2026-07-05T13:02:13+00:00",
    "type": "inflow",
    "frxusd": 143.0,
    "asset": "USDC",
    "assetAmount": 143.0,
    "assetValueUSD": 143.0,
    "txUrl": "https://etherscan.io/tx/0x0a98912c5debb35fe6882d8d8364dd2c7733c8c46218874d075c57802133e576"
  },
  {
    "ts": "2026-07-05T12:59:01+00:00",
    "type": "inflow",
    "frxusd": 197.26,
    "asset": "USDC",
    "assetAmount": 197.26,
    "assetValueUSD": 197.26,
    "txUrl": "https://etherscan.io/tx/0x52909c242acb96b2c4b31ce660d081d81c3fa8096792282c2fffa231b73d71af"
  },
  {
    "ts": "2026-07-05T12:58:25+00:00",
    "type": "inflow",
    "frxusd": 2216.88,
    "asset": "USDC",
    "assetAmount": 2216.88,
    "assetValueUSD": 2216.88,
    "txUrl": "https://etherscan.io/tx/0xb352b4614ac634ce0ed7f96164452f6bac9b0d2f652801c76615be4c5a0422a1"
  },
  {
    "ts": "2026-07-05T12:57:50+00:00",
    "type": "inflow",
    "frxusd": 49808.77,
    "asset": "USDC",
    "assetAmount": 49808.77,
    "assetValueUSD": 49808.77,
    "txUrl": "https://etherscan.io/tx/0x2f777b906b91a298bd55f37c3030d9497e5332712c552db42674d67b4633723e"
  },
  {
    "ts": "2026-07-05T12:56:49+00:00",
    "type": "inflow",
    "frxusd": 2900.95,
    "asset": "USDC",
    "assetAmount": 2900.95,
    "assetValueUSD": 2900.95,
    "txUrl": "https://etherscan.io/tx/0xb6257e0e2ff114d853d527c4b23c7ef42888b09272834ba9093d7c9701360d4d"
  },
  {
    "ts": "2026-07-05T12:56:38+00:00",
    "type": "outflow",
    "frxusd": 1240.17,
    "asset": "USTB",
    "assetAmount": 111.35,
    "assetValueUSD": 1240.05,
    "txUrl": "https://etherscan.io/tx/0x95ae03b880b0315bf7a0477f79c6bf35e0227d743aa8b51584338554288e7ef5"
  },
  {
    "ts": "2026-07-05T11:34:37+00:00",
    "type": "outflow",
    "frxusd": 593.46,
    "asset": "USDC",
    "assetAmount": 593.46,
    "assetValueUSD": 593.46,
    "txUrl": "https://etherscan.io/tx/0xd606ec7b7fd549de2b9f6396da02df5469532f8a344654b531f8b295123cc8bd"
  },
  {
    "ts": "2026-07-05T11:23:01+00:00",
    "type": "outflow",
    "frxusd": 1874.92,
    "asset": "USDC",
    "assetAmount": 1874.92,
    "assetValueUSD": 1874.92,
    "txUrl": "https://etherscan.io/tx/0xab72676c08d5493b331881da5f5205757eeeecd1d49e79c7f2be4313177e1e30"
  },
  {
    "ts": "2026-07-05T11:16:49+00:00",
    "type": "outflow",
    "frxusd": 1246.48,
    "asset": "USDC",
    "assetAmount": 1246.48,
    "assetValueUSD": 1246.48,
    "txUrl": "https://etherscan.io/tx/0x078d8df28a98ac43f6fa7fde5297f9964462e1dee287f7c90170144e7ce4c2ee"
  },
  {
    "ts": "2026-07-05T11:16:25+00:00",
    "type": "outflow",
    "frxusd": 1782.48,
    "asset": "USDC",
    "assetAmount": 1782.48,
    "assetValueUSD": 1782.48,
    "txUrl": "https://etherscan.io/tx/0xfa5d83d548fd25e3debabd743803016182c9eedc1b936d9a32af5760f2e294e8"
  },
  {
    "ts": "2026-07-05T10:45:01+00:00",
    "type": "outflow",
    "frxusd": 1805.46,
    "asset": "USDC",
    "assetAmount": 1805.46,
    "assetValueUSD": 1805.46,
    "txUrl": "https://etherscan.io/tx/0x08bbe8984155ab8c31983ea2b0448883a092c39c1b79a84c8a23fae79670172f"
  },
  {
    "ts": "2026-07-05T10:44:37+00:00",
    "type": "outflow",
    "frxusd": 3695.54,
    "asset": "USDC",
    "assetAmount": 3695.54,
    "assetValueUSD": 3695.54,
    "txUrl": "https://etherscan.io/tx/0x9c92a5d8989b53c1ef048e329eeafbd6718f997320897295dbcb995db6bdc5f9"
  },
  {
    "ts": "2026-07-05T10:44:15+00:00",
    "type": "outflow",
    "frxusd": 19024.59,
    "asset": "USDC",
    "assetAmount": 19024.59,
    "assetValueUSD": 19024.59,
    "txUrl": "https://etherscan.io/tx/0x2a48abbc867fc358fd6b9375292d372a02aad796e01c01206be2ce2068d61f4e"
  },
  {
    "ts": "2026-07-05T10:44:14+00:00",
    "type": "inflow",
    "frxusd": 30015.45,
    "asset": "USDC",
    "assetAmount": 30015.45,
    "assetValueUSD": 30015.45,
    "txUrl": "https://etherscan.io/tx/0x71cffafe5d1548ed4aaeb889aa471c9bae64f12f04a792c62f22717e13649e66"
  },
  {
    "ts": "2026-07-05T10:41:38+00:00",
    "type": "inflow",
    "frxusd": 15.82,
    "asset": "USDC",
    "assetAmount": 15.82,
    "assetValueUSD": 15.82,
    "txUrl": "https://etherscan.io/tx/0xa827b30cf8baa6b09ec103a1e2d3b74ae0a2d63ed9ca878c2f7009a1ae3f25fd"
  },
  {
    "ts": "2026-07-05T10:26:25+00:00",
    "type": "outflow",
    "frxusd": 4912.17,
    "asset": "USTB",
    "assetAmount": 441.07,
    "assetValueUSD": 4911.68,
    "txUrl": "https://etherscan.io/tx/0x63893e6dab6c4552b13ac5698fff176f640852aacdd18b3133e7d5b8ef99d0c7"
  },
  {
    "ts": "2026-07-05T10:15:26+00:00",
    "type": "outflow",
    "frxusd": 1801.83,
    "asset": "USTB",
    "assetAmount": 161.78,
    "assetValueUSD": 1801.65,
    "txUrl": "https://etherscan.io/tx/0xa1b5316aef2c353ea389e6a4acdd1ce1911a65798212922b7d4cce4cc3fd0d7a"
  },
  {
    "ts": "2026-07-05T09:54:03+00:00",
    "type": "inflow",
    "frxusd": 29.98,
    "asset": "USDC",
    "assetAmount": 29.98,
    "assetValueUSD": 29.98,
    "txUrl": "https://etherscan.io/tx/0xb73fc7a0b5c502fe96de4d17cca31ad749a01d3186696abd2dd65e05238c2ad2"
  },
  {
    "ts": "2026-07-05T09:42:01+00:00",
    "type": "outflow",
    "frxusd": 5173.49,
    "asset": "USTB",
    "assetAmount": 464.53,
    "assetValueUSD": 5172.98,
    "txUrl": "https://etherscan.io/tx/0x218b8e9495c279ad5f7307f5ca6e3617186ac4750c9db4a2913c8fcf79e4df87"
  },
  {
    "ts": "2026-07-05T09:41:50+00:00",
    "type": "outflow",
    "frxusd": 20385.72,
    "asset": "USTB",
    "assetAmount": 1830.46,
    "assetValueUSD": 20383.68,
    "txUrl": "https://etherscan.io/tx/0x84dc617162cc3deb2f3c24358c8ccf95cbe01614f572867903371950703a5946"
  },
  {
    "ts": "2026-07-05T09:41:49+00:00",
    "type": "outflow",
    "frxusd": 28123.66,
    "asset": "USTB",
    "assetAmount": 2525.27,
    "assetValueUSD": 28120.85,
    "txUrl": "https://etherscan.io/tx/0x69c7b69bb11b6dd5cc2c1e1923532f900ac4f7386070f46a46e9dc2fb690d1c8"
  },
  {
    "ts": "2026-07-05T09:40:37+00:00",
    "type": "outflow",
    "frxusd": 141.17,
    "asset": "USDC",
    "assetAmount": 141.17,
    "assetValueUSD": 141.17,
    "txUrl": "https://etherscan.io/tx/0xef5048a6b8fc330c9fbf95f2aa7e959a81701caa0e9b8b3ee72acafe39068010"
  },
  {
    "ts": "2026-07-05T09:14:49+00:00",
    "type": "outflow",
    "frxusd": 2453.46,
    "asset": "USTB",
    "assetAmount": 220.3,
    "assetValueUSD": 2453.22,
    "txUrl": "https://etherscan.io/tx/0xbe2ff641b3892ce8a7751a681b972ea37aef2b267711987a6d5ad3f542473a1e"
  },
  {
    "ts": "2026-07-05T09:14:38+00:00",
    "type": "outflow",
    "frxusd": 1774.08,
    "asset": "USDC",
    "assetAmount": 1774.08,
    "assetValueUSD": 1774.08,
    "txUrl": "https://etherscan.io/tx/0x4fdcc9da88f517dde2b4ef94b44a68069cfebd4f1b369a782c8b9427e57d5147"
  },
  {
    "ts": "2026-07-05T09:14:37+00:00",
    "type": "outflow",
    "frxusd": 663.0,
    "asset": "USTB",
    "assetAmount": 59.53,
    "assetValueUSD": 662.93,
    "txUrl": "https://etherscan.io/tx/0x4067e4dd817d024c31e3cb3b9d8a90afc137a4a172b43d368eec880509462fdb"
  },
  {
    "ts": "2026-07-05T09:14:27+00:00",
    "type": "outflow",
    "frxusd": 1805.44,
    "asset": "USDC",
    "assetAmount": 1805.44,
    "assetValueUSD": 1805.44,
    "txUrl": "https://etherscan.io/tx/0xab409b28bd69136c9ec1424a60c56703c30269d5531661bcae50e8e924732770"
  },
  {
    "ts": "2026-07-05T09:14:25+00:00",
    "type": "inflow",
    "frxusd": 732.99,
    "asset": "USDC",
    "assetAmount": 732.99,
    "assetValueUSD": 732.99,
    "txUrl": "https://etherscan.io/tx/0x5ea3b9e30d0c3519d30c9b84a0344bc004bed9039ebdbd0b0d21986c1f1df11c"
  },
  {
    "ts": "2026-07-05T09:01:25+00:00",
    "type": "inflow",
    "frxusd": 2734.69,
    "asset": "USDC",
    "assetAmount": 2734.69,
    "assetValueUSD": 2734.69,
    "txUrl": "https://etherscan.io/tx/0x72822c1d8b97b385a706c4bc821b10df80121c720119e94c8498df39a6cf416e"
  },
  {
    "ts": "2026-07-05T08:27:49+00:00",
    "type": "outflow",
    "frxusd": 5.09,
    "asset": "USDC",
    "assetAmount": 5.09,
    "assetValueUSD": 5.09,
    "txUrl": "https://etherscan.io/tx/0xad829b75b19e5bbba19faf7bf4fd615c118fa3aed156e27ac3c40d61b4d21305"
  },
  {
    "ts": "2026-07-05T08:27:25+00:00",
    "type": "outflow",
    "frxusd": 31000.0,
    "asset": "USDC",
    "assetAmount": 31000.0,
    "assetValueUSD": 31000.0,
    "txUrl": "https://etherscan.io/tx/0x38ef5ae26d5df02b8eefdd6137866abc028cd077206f6c58607c556b222b8622"
  },
  {
    "ts": "2026-07-05T08:26:25+00:00",
    "type": "outflow",
    "frxusd": 1191.99,
    "asset": "USDC",
    "assetAmount": 1191.99,
    "assetValueUSD": 1191.99,
    "txUrl": "https://etherscan.io/tx/0x94dce66d8ff4a6ca6718fb3084a3e6b8153c781ea5f20ba4be64b122b10f9d13"
  },
  {
    "ts": "2026-07-05T08:17:25+00:00",
    "type": "inflow",
    "frxusd": 32097.71,
    "asset": "USDC",
    "assetAmount": 32097.71,
    "assetValueUSD": 32097.71,
    "txUrl": "https://etherscan.io/tx/0xea5a51772ee82c3125fe2a9a1825c4672480cf9cbb9ae9444a3432b1a329f50a"
  },
  {
    "ts": "2026-07-05T08:13:25+00:00",
    "type": "outflow",
    "frxusd": 87000.0,
    "asset": "USDC",
    "assetAmount": 87000.0,
    "assetValueUSD": 87000.0,
    "txUrl": "https://etherscan.io/tx/0xef870d717fe02edd3f057aa01da6e9e8d25674379ff907f00d5961031498ff28"
  },
  {
    "ts": "2026-07-05T08:11:50+00:00",
    "type": "outflow",
    "frxusd": 100000.0,
    "asset": "USDC",
    "assetAmount": 100000.0,
    "assetValueUSD": 100000.0,
    "txUrl": "https://etherscan.io/tx/0x705499170ff7d93e2203a79f27efe2a210856224eb217493e6ad13b03f04ce08"
  },
  {
    "ts": "2026-07-05T07:55:13+00:00",
    "type": "inflow",
    "frxusd": 10.0,
    "asset": "USDC",
    "assetAmount": 10.0,
    "assetValueUSD": 10.0,
    "txUrl": "https://etherscan.io/tx/0x8a3d157494dd36020d0053b2f2391c20194a3cbd76625cbeed6e257bf0da4f20"
  },
  {
    "ts": "2026-07-05T07:53:39+00:00",
    "type": "inflow",
    "frxusd": 900.0,
    "asset": "USDC",
    "assetAmount": 900.0,
    "assetValueUSD": 900.0,
    "txUrl": "https://etherscan.io/tx/0xad2d869ee0e55b89c8de74e21809d4e80a6530cf4e3147b33001db5ed5f122d9"
  },
  {
    "ts": "2026-07-05T07:52:13+00:00",
    "type": "inflow",
    "frxusd": 5002.0,
    "asset": "USDC",
    "assetAmount": 5002.0,
    "assetValueUSD": 5002.0,
    "txUrl": "https://etherscan.io/tx/0x59c710162afc9319c9e90a2845b7e48ed6432bfee0115ee17d7331776e25758a"
  },
  {
    "ts": "2026-07-05T07:36:37+00:00",
    "type": "outflow",
    "frxusd": 1.68,
    "asset": "USDC",
    "assetAmount": 1.68,
    "assetValueUSD": 1.68,
    "txUrl": "https://etherscan.io/tx/0x24d0e124e9a2a2554141100b41d50a09a8f089a553859ef764be46951a4edbbe"
  },
  {
    "ts": "2026-07-05T07:32:51+00:00",
    "type": "inflow",
    "frxusd": 1511.36,
    "asset": "USDC",
    "assetAmount": 1511.36,
    "assetValueUSD": 1511.36,
    "txUrl": "https://etherscan.io/tx/0x662bddf0c038a6d1a770aca64dc88de4ca87dc648aade685b6259d6798d6e172"
  },
  {
    "ts": "2026-07-05T07:31:50+00:00",
    "type": "inflow",
    "frxusd": 47.59,
    "asset": "USDC",
    "assetAmount": 47.59,
    "assetValueUSD": 47.59,
    "txUrl": "https://etherscan.io/tx/0xd6f3e6aa402ef8c601b2b5078de25f452f2e8a0b9f40a786f14a306d1e449ad8"
  },
  {
    "ts": "2026-07-05T07:26:01+00:00",
    "type": "outflow",
    "frxusd": 77.8,
    "asset": "USDC",
    "assetAmount": 77.8,
    "assetValueUSD": 77.8,
    "txUrl": "https://etherscan.io/tx/0x096816b1cf59ea664e0c3d1aab1f9867cf063475cc19a7a04bf9410f8695d44f"
  },
  {
    "ts": "2026-07-05T07:20:13+00:00",
    "type": "outflow",
    "frxusd": 100.84,
    "asset": "USDC",
    "assetAmount": 100.84,
    "assetValueUSD": 100.84,
    "txUrl": "https://etherscan.io/tx/0x5347f5a98e779f2f29edc29a00385e7fa6f3253396299b0d77d6a253c94e70cd"
  },
  {
    "ts": "2026-07-05T07:17:01+00:00",
    "type": "inflow",
    "frxusd": 62.01,
    "asset": "USDC",
    "assetAmount": 62.01,
    "assetValueUSD": 62.01,
    "txUrl": "https://etherscan.io/tx/0xf2625a3a35cbdbf7fca80cbe944f34879909be89aaa299cd60660278c9b5ee0f"
  },
  {
    "ts": "2026-07-05T07:14:15+00:00",
    "type": "inflow",
    "frxusd": 61.68,
    "asset": "USDC",
    "assetAmount": 61.68,
    "assetValueUSD": 61.68,
    "txUrl": "https://etherscan.io/tx/0x0dd2068631acc869f55d890b43b95d8ece4845b07bda59eeb754928414947f5d"
  },
  {
    "ts": "2026-07-05T07:08:49+00:00",
    "type": "inflow",
    "frxusd": 1656.84,
    "asset": "USDC",
    "assetAmount": 1656.84,
    "assetValueUSD": 1656.84,
    "txUrl": "https://etherscan.io/tx/0x6c58415ffeae7c3b33c8bf70b94ace2ba090fe90ff6fc656fda126e13b83544a"
  },
  {
    "ts": "2026-07-05T06:59:25+00:00",
    "type": "inflow",
    "frxusd": 1283.91,
    "asset": "USDC",
    "assetAmount": 1283.91,
    "assetValueUSD": 1283.91,
    "txUrl": "https://etherscan.io/tx/0xc6face8f40cb065a84305fa7baba1cd9f139045ef4ced89e6b99c8f6eabc3454"
  },
  {
    "ts": "2026-07-05T06:48:13+00:00",
    "type": "inflow",
    "frxusd": 41789.06,
    "asset": "USDC",
    "assetAmount": 41789.06,
    "assetValueUSD": 41789.06,
    "txUrl": "https://etherscan.io/tx/0xcf2128774cbf9d11bf2582d6c7f29ebf5851ea28e469e12f3ec9d7f056a1d8f7"
  },
  {
    "ts": "2026-07-05T06:38:26+00:00",
    "type": "inflow",
    "frxusd": 176.42,
    "asset": "USDC",
    "assetAmount": 176.42,
    "assetValueUSD": 176.42,
    "txUrl": "https://etherscan.io/tx/0x3d6af443494b5b852973ff93428e9fc6d4c35fa02dae48043b4ed9fddfd94607"
  },
  {
    "ts": "2026-07-05T06:17:27+00:00",
    "type": "inflow",
    "frxusd": 44568.09,
    "asset": "USDC",
    "assetAmount": 44568.09,
    "assetValueUSD": 44568.09,
    "txUrl": "https://etherscan.io/tx/0x1c99fb28f1694b69d61daf8daccf99404c6f44ddb6d8a91ba5b35fd5503ceca1"
  },
  {
    "ts": "2026-07-05T06:17:26+00:00",
    "type": "inflow",
    "frxusd": 9000.59,
    "asset": "USDC",
    "assetAmount": 9000.59,
    "assetValueUSD": 9000.59,
    "txUrl": "https://etherscan.io/tx/0xdf971903772a1971e993f017b8a71d44d5efe711fe10d32c2ebd63e7e280f279"
  },
  {
    "ts": "2026-07-05T06:13:50+00:00",
    "type": "outflow",
    "frxusd": 9007.0,
    "asset": "USDC",
    "assetAmount": 9007.0,
    "assetValueUSD": 9007.0,
    "txUrl": "https://etherscan.io/tx/0xb69da3fed85c469cae8704508b2dc8d29801007b5830980bdabab1ae46300664"
  },
  {
    "ts": "2026-07-05T06:13:50+00:00",
    "type": "outflow",
    "frxusd": 3696.55,
    "asset": "USDC",
    "assetAmount": 3696.55,
    "assetValueUSD": 3696.55,
    "txUrl": "https://etherscan.io/tx/0x56f15a27a8b07e96d3769483044a713ad5eedf48840bfa9372f4e4cdf0cef7c2"
  },
  {
    "ts": "2026-07-05T06:13:39+00:00",
    "type": "outflow",
    "frxusd": 6438.76,
    "asset": "USDC",
    "assetAmount": 6438.76,
    "assetValueUSD": 6438.76,
    "txUrl": "https://etherscan.io/tx/0xf21ffe3a84b7582de0830068ef871a77aa776f0a42faf88346b82f49f4b8e357"
  },
  {
    "ts": "2026-07-05T06:13:38+00:00",
    "type": "inflow",
    "frxusd": 20000.0,
    "asset": "USDC",
    "assetAmount": 20000.0,
    "assetValueUSD": 20000.0,
    "txUrl": "https://etherscan.io/tx/0xf447916904d179413a78aecb0b91b46258b6089ef2812da16d407a8d4905673d"
  },
  {
    "ts": "2026-07-05T06:10:25+00:00",
    "type": "outflow",
    "frxusd": 2845.82,
    "asset": "USDC",
    "assetAmount": 2845.82,
    "assetValueUSD": 2845.82,
    "txUrl": "https://etherscan.io/tx/0xc5103e67e60994aa49f4ca0dbbcf343ed4b0550df25b28ed2c5bc31edc3a0a61"
  },
  {
    "ts": "2026-07-05T06:03:37+00:00",
    "type": "inflow",
    "frxusd": 3951.73,
    "asset": "USDC",
    "assetAmount": 3951.73,
    "assetValueUSD": 3951.73,
    "txUrl": "https://etherscan.io/tx/0x99e457436dd16195d9a53acc9c827d1a2dacd902cc9c9a62dfe044a02c1b38dd"
  },
  {
    "ts": "2026-07-05T06:02:14+00:00",
    "type": "inflow",
    "frxusd": 1200.0,
    "asset": "USDC",
    "assetAmount": 1200.0,
    "assetValueUSD": 1200.0,
    "txUrl": "https://etherscan.io/tx/0x1846c146151cd0eecb6cdea6b7c0baa5065c5770fb30be4dd492a9d84ec5fcd3"
  },
  {
    "ts": "2026-07-05T05:52:01+00:00",
    "type": "outflow",
    "frxusd": 9009.07,
    "asset": "USDC",
    "assetAmount": 9009.07,
    "assetValueUSD": 9009.07,
    "txUrl": "https://etherscan.io/tx/0xf003a541503d7e56b9a594f27315c28778aa1d706872394b534fcba2fd2f8be1"
  },
  {
    "ts": "2026-07-05T05:43:25+00:00",
    "type": "inflow",
    "frxusd": 20000.0,
    "asset": "USDC",
    "assetAmount": 20000.0,
    "assetValueUSD": 20000.0,
    "txUrl": "https://etherscan.io/tx/0xb200d102f94a3b70182995c5aca40737ad975c5259e354480752f1630176fcea"
  },
  {
    "ts": "2026-07-05T05:33:49+00:00",
    "type": "outflow",
    "frxusd": 976.83,
    "asset": "USDC",
    "assetAmount": 976.83,
    "assetValueUSD": 976.83,
    "txUrl": "https://etherscan.io/tx/0xd7b36c3ab7c30709fd4cf0804e3ef65840a8d51de9152dc1f2fe90681b374943"
  },
  {
    "ts": "2026-07-05T05:15:25+00:00",
    "type": "outflow",
    "frxusd": 4729.64,
    "asset": "USDC",
    "assetAmount": 4729.64,
    "assetValueUSD": 4729.64,
    "txUrl": "https://etherscan.io/tx/0xcc17046d67b9cc1a3e505cde8c8d7618d9bc5653d3b7e1cbafae4c844d4628c1"
  },
  {
    "ts": "2026-07-05T05:00:50+00:00",
    "type": "inflow",
    "frxusd": 100.0,
    "asset": "USDC",
    "assetAmount": 100.0,
    "assetValueUSD": 100.0,
    "txUrl": "https://etherscan.io/tx/0x90da3f6bad5f05a7730f316d2694225b927670888acb01811fcfeb5efd835ca3"
  },
  {
    "ts": "2026-07-05T03:34:54+00:00",
    "type": "outflow",
    "frxusd": 16.74,
    "asset": "USDC",
    "assetAmount": 16.74,
    "assetValueUSD": 16.74,
    "txUrl": "https://etherscan.io/tx/0xb91cbe41d6ce91b0181fac3b7da8d6d5600708a4d05632fac1408902ee3ec098"
  },
  {
    "ts": "2026-07-05T03:21:13+00:00",
    "type": "outflow",
    "frxusd": 1329.38,
    "asset": "USDC",
    "assetAmount": 1329.38,
    "assetValueUSD": 1329.38,
    "txUrl": "https://etherscan.io/tx/0xae30950c95bda8b55596823069495803befee0a3c8526a11748a317972d055a2"
  },
  {
    "ts": "2026-07-05T03:13:02+00:00",
    "type": "outflow",
    "frxusd": 50.35,
    "asset": "USDC",
    "assetAmount": 50.35,
    "assetValueUSD": 50.35,
    "txUrl": "https://etherscan.io/tx/0xfa31b808f53d40b939c0155a82b66075a425ce209753af5f544e308d605689b7"
  },
  {
    "ts": "2026-07-05T03:10:37+00:00",
    "type": "outflow",
    "frxusd": 271.15,
    "asset": "USDC",
    "assetAmount": 271.15,
    "assetValueUSD": 271.15,
    "txUrl": "https://etherscan.io/tx/0x7977027b3cfb99e8bd096aa49b604f2823a5d58ec65367d3046827d392b13d2c"
  },
  {
    "ts": "2026-07-05T03:10:14+00:00",
    "type": "outflow",
    "frxusd": 74.02,
    "asset": "USDC",
    "assetAmount": 74.02,
    "assetValueUSD": 74.02,
    "txUrl": "https://etherscan.io/tx/0xbbfb382a8e3f7396b2a0bb2733937483f51a8407c75de764aec0af847cf7a1fd"
  },
  {
    "ts": "2026-07-05T03:09:49+00:00",
    "type": "outflow",
    "frxusd": 144.96,
    "asset": "USDC",
    "assetAmount": 144.96,
    "assetValueUSD": 144.96,
    "txUrl": "https://etherscan.io/tx/0x91b8f6d51b2294d2542479e92ff1553e8bf366e78109d67355d4a0f0bea3d04a"
  },
  {
    "ts": "2026-07-05T03:02:54+00:00",
    "type": "outflow",
    "frxusd": 78.93,
    "asset": "USDC",
    "assetAmount": 78.93,
    "assetValueUSD": 78.93,
    "txUrl": "https://etherscan.io/tx/0x2beebd884ffe93322c09a42af110d9468857e51c292b62b45bdeb5a37d82e3b0"
  },
  {
    "ts": "2026-07-05T03:00:26+00:00",
    "type": "inflow",
    "frxusd": 11209.42,
    "asset": "USDC",
    "assetAmount": 11209.42,
    "assetValueUSD": 11209.42,
    "txUrl": "https://etherscan.io/tx/0xc00d14b6817153b3f2de05c7e88f53c2e6f056d4839cd53c955dbd009bf50e98"
  },
  {
    "ts": "2026-07-05T02:59:01+00:00",
    "type": "inflow",
    "frxusd": 17707.34,
    "asset": "USDC",
    "assetAmount": 17707.34,
    "assetValueUSD": 17707.34,
    "txUrl": "https://etherscan.io/tx/0xdbd23cf0f779499a5b122c64b0b45609c1357feb3a2f44c14ba455b0ee7a6e1c"
  },
  {
    "ts": "2026-07-05T02:54:51+00:00",
    "type": "inflow",
    "frxusd": 20016.17,
    "asset": "USDC",
    "assetAmount": 20016.17,
    "assetValueUSD": 20016.17,
    "txUrl": "https://etherscan.io/tx/0x073de5b7762ca0eba0876f65e01402fc906b9e30c9a351e072494eb921fd1c06"
  },
  {
    "ts": "2026-07-05T02:53:25+00:00",
    "type": "inflow",
    "frxusd": 6212.36,
    "asset": "USDC",
    "assetAmount": 6212.36,
    "assetValueUSD": 6212.36,
    "txUrl": "https://etherscan.io/tx/0x483893b87e80d0fb7093c4cf28848f4a411629f00e9fb1b415ab50ac7370abdd"
  },
  {
    "ts": "2026-07-05T02:45:14+00:00",
    "type": "outflow",
    "frxusd": 489.51,
    "asset": "USDC",
    "assetAmount": 489.51,
    "assetValueUSD": 489.51,
    "txUrl": "https://etherscan.io/tx/0xa3dc6728f586bfe070fc0095cce8f388ca983e5b31bd13c4c74dce9507955e42"
  },
  {
    "ts": "2026-07-05T02:45:01+00:00",
    "type": "outflow",
    "frxusd": 578.08,
    "asset": "USDC",
    "assetAmount": 578.08,
    "assetValueUSD": 578.08,
    "txUrl": "https://etherscan.io/tx/0xb3ee43c9793c56d43949c669b6eda0ca64fe37162857db983c3cb76f857629c3"
  },
  {
    "ts": "2026-07-05T02:43:49+00:00",
    "type": "outflow",
    "frxusd": 980.2,
    "asset": "USDC",
    "assetAmount": 980.2,
    "assetValueUSD": 980.2,
    "txUrl": "https://etherscan.io/tx/0xfc721df2068eeefc3c86da7659ffee5ac841a7e7b4096efe9285bfe2940afca9"
  },
  {
    "ts": "2026-07-05T02:43:26+00:00",
    "type": "outflow",
    "frxusd": 5431.19,
    "asset": "USDC",
    "assetAmount": 5431.19,
    "assetValueUSD": 5431.19,
    "txUrl": "https://etherscan.io/tx/0x01f2252a960e8a1ae4faaa3be775523065c64a6285e2c7b719afe5b18a9b6adc"
  },
  {
    "ts": "2026-07-05T02:43:01+00:00",
    "type": "inflow",
    "frxusd": 13504.91,
    "asset": "USDC",
    "assetAmount": 13504.91,
    "assetValueUSD": 13504.91,
    "txUrl": "https://etherscan.io/tx/0x331d93d6847b1e88d6b4b7dc2d9a07a51e5034ba8aa8eee9bbb536cbd9f0064d"
  },
  {
    "ts": "2026-07-05T02:29:01+00:00",
    "type": "outflow",
    "frxusd": 490.9,
    "asset": "USDC",
    "assetAmount": 490.9,
    "assetValueUSD": 490.9,
    "txUrl": "https://etherscan.io/tx/0x628dd1ff999f9a49838b1e6858a57e3b02a7d75aae69262d52146f725c7e247e"
  },
  {
    "ts": "2026-07-05T02:28:25+00:00",
    "type": "inflow",
    "frxusd": 14043.27,
    "asset": "USDC",
    "assetAmount": 14043.27,
    "assetValueUSD": 14043.27,
    "txUrl": "https://etherscan.io/tx/0xf173748a788b92421f39371b8263ecdb66cd46b629bba5c7c1809517ad960a7a"
  },
  {
    "ts": "2026-07-05T02:23:49+00:00",
    "type": "outflow",
    "frxusd": 22404.18,
    "asset": "USDC",
    "assetAmount": 22404.18,
    "assetValueUSD": 22404.18,
    "txUrl": "https://etherscan.io/tx/0xd43071b2921a4f4056483906cebc7186ae0442c75f09a5caaac90617a34e6472"
  },
  {
    "ts": "2026-07-05T02:23:37+00:00",
    "type": "inflow",
    "frxusd": 22500.0,
    "asset": "USDC",
    "assetAmount": 22500.0,
    "assetValueUSD": 22500.0,
    "txUrl": "https://etherscan.io/tx/0x0100bd7ac277a148fc37de43a7dddc5bac258d422e9ae4db06e7055869d5a557"
  },
  {
    "ts": "2026-07-05T02:02:26+00:00",
    "type": "outflow",
    "frxusd": 4.83,
    "asset": "USDC",
    "assetAmount": 4.83,
    "assetValueUSD": 4.83,
    "txUrl": "https://etherscan.io/tx/0x61854f4084d5b4977c969f85e36bea17ef70cbc84a98c8c2bebe9282a55ebf2f"
  },
  {
    "ts": "2026-07-05T01:59:02+00:00",
    "type": "outflow",
    "frxusd": 1.25,
    "asset": "USDC",
    "assetAmount": 1.25,
    "assetValueUSD": 1.25,
    "txUrl": "https://etherscan.io/tx/0xa3402a36e75eb5f447fa38776f8380f6d9ac3b620d966bf5afb5a1f822c0435a"
  },
  {
    "ts": "2026-07-05T01:46:49+00:00",
    "type": "outflow",
    "frxusd": 37466.04,
    "asset": "USDC",
    "assetAmount": 37466.04,
    "assetValueUSD": 37466.04,
    "txUrl": "https://etherscan.io/tx/0xefbe88af2529733771b12cd1ad8a95cdfb0f75cacb2d0399d995c1af2eb3b373"
  },
  {
    "ts": "2026-07-05T01:39:13+00:00",
    "type": "outflow",
    "frxusd": 1152.02,
    "asset": "USDC",
    "assetAmount": 1152.02,
    "assetValueUSD": 1152.02,
    "txUrl": "https://etherscan.io/tx/0xf27b4b30ec6c93eebacfd5ba055d51a54fc928b3483cd79248eedae7730d7fff"
  },
  {
    "ts": "2026-07-05T01:38:37+00:00",
    "type": "outflow",
    "frxusd": 3476.03,
    "asset": "USDC",
    "assetAmount": 3476.03,
    "assetValueUSD": 3476.03,
    "txUrl": "https://etherscan.io/tx/0x29f2ac38bda18b57360355bc0e801366ac5db97e12f15385d2b3f8f8052d5f22"
  },
  {
    "ts": "2026-07-05T01:38:01+00:00",
    "type": "outflow",
    "frxusd": 808.83,
    "asset": "USDC",
    "assetAmount": 808.83,
    "assetValueUSD": 808.83,
    "txUrl": "https://etherscan.io/tx/0x7d0ccf449f930497cee0909ff56f5674b9310e8c53d7d0b62f24674fea326690"
  },
  {
    "ts": "2026-07-05T01:34:49+00:00",
    "type": "outflow",
    "frxusd": 917.36,
    "asset": "USDC",
    "assetAmount": 917.36,
    "assetValueUSD": 917.36,
    "txUrl": "https://etherscan.io/tx/0xd07a50ff4ecd2a45b4005b41a8db1e47fe726ba3ed554694379a121d9d449d22"
  },
  {
    "ts": "2026-07-05T01:33:39+00:00",
    "type": "outflow",
    "frxusd": 1455.9,
    "asset": "USDC",
    "assetAmount": 1455.9,
    "assetValueUSD": 1455.9,
    "txUrl": "https://etherscan.io/tx/0x2f8efdfb6d4130f76e9f33cc9da1a6a3525727eb28c27d79625a05420e390add"
  },
  {
    "ts": "2026-07-05T01:20:50+00:00",
    "type": "outflow",
    "frxusd": 983.53,
    "asset": "USDC",
    "assetAmount": 983.53,
    "assetValueUSD": 983.53,
    "txUrl": "https://etherscan.io/tx/0x0c16706c571fc9723832a11c8f035251b2d9ffb80a13eb072f8ea562bfe0f462"
  },
  {
    "ts": "2026-07-05T01:17:13+00:00",
    "type": "outflow",
    "frxusd": 985.68,
    "asset": "USDC",
    "assetAmount": 985.68,
    "assetValueUSD": 985.68,
    "txUrl": "https://etherscan.io/tx/0x07664053e3b3229e61b1fa8da2078af8a65ce310618f5af72b742589947f5cbb"
  },
  {
    "ts": "2026-07-05T01:14:49+00:00",
    "type": "inflow",
    "frxusd": 56.7,
    "asset": "USDC",
    "assetAmount": 56.7,
    "assetValueUSD": 56.7,
    "txUrl": "https://etherscan.io/tx/0x6347fdd214f9ac56c0690385e49433ac9df4edb9c337a84895b0667e2544207e"
  },
  {
    "ts": "2026-07-05T01:10:27+00:00",
    "type": "inflow",
    "frxusd": 77.05,
    "asset": "USDC",
    "assetAmount": 77.05,
    "assetValueUSD": 77.05,
    "txUrl": "https://etherscan.io/tx/0x456094af8581133fae34a1fca70a355161df6231f538a6a0b8197a0c26df3fdd"
  },
  {
    "ts": "2026-07-05T00:51:14+00:00",
    "type": "outflow",
    "frxusd": 73.34,
    "asset": "USDC",
    "assetAmount": 73.34,
    "assetValueUSD": 73.34,
    "txUrl": "https://etherscan.io/tx/0xeee2c6ef4cf6118b9fc86dd7b659b7fe43d3a7aacb5fc7530ff99d07f721659c"
  },
  {
    "ts": "2026-07-05T00:29:38+00:00",
    "type": "outflow",
    "frxusd": 3316.77,
    "asset": "USDC",
    "assetAmount": 3316.77,
    "assetValueUSD": 3316.77,
    "txUrl": "https://etherscan.io/tx/0x2d161b6c77304ba30e9d9479e47a46adcd520da726d24bcaa9068040b7d612ca"
  },
  {
    "ts": "2026-07-05T00:20:14+00:00",
    "type": "inflow",
    "frxusd": 999.89,
    "asset": "USDC",
    "assetAmount": 999.89,
    "assetValueUSD": 999.89,
    "txUrl": "https://etherscan.io/tx/0x47d94e51fc49f6ca11decf14def56f61ce916391a53274af6f4640533a2f8c1f"
  },
  {
    "ts": "2026-07-05T00:02:25+00:00",
    "type": "outflow",
    "frxusd": 688.25,
    "asset": "USDC",
    "assetAmount": 688.25,
    "assetValueUSD": 688.25,
    "txUrl": "https://etherscan.io/tx/0xb5c30353c732cd85239636b7144f1dccd00e5916a531c6a5052dd3fa5326babf"
  },
  {
    "ts": "2026-07-04T23:59:50+00:00",
    "type": "outflow",
    "frxusd": 54840.94,
    "asset": "USDC",
    "assetAmount": 54840.94,
    "assetValueUSD": 54840.94,
    "txUrl": "https://etherscan.io/tx/0x75dd240597f999c38c048eaac2f161d4291d6ac6e06be1b6110259212bb534db"
  },
  {
    "ts": "2026-07-04T23:58:25+00:00",
    "type": "inflow",
    "frxusd": 1000.0,
    "asset": "USDC",
    "assetAmount": 1000.0,
    "assetValueUSD": 1000.0,
    "txUrl": "https://etherscan.io/tx/0xc517b093c9cc3869d5bbc3a3d297fab0e4b818245a62063146ebb8f365b8827f"
  },
  {
    "ts": "2026-07-04T23:57:25+00:00",
    "type": "outflow",
    "frxusd": 14360.75,
    "asset": "USDC",
    "assetAmount": 14360.75,
    "assetValueUSD": 14360.75,
    "txUrl": "https://etherscan.io/tx/0x75b2b0e983c62857c595ecb27e3cf4fd72b64b2fce9b3bb46d3db14923be1ea0"
  },
  {
    "ts": "2026-07-04T23:57:16+00:00",
    "type": "inflow",
    "frxusd": 98168.25,
    "asset": "USDC",
    "assetAmount": 98168.25,
    "assetValueUSD": 98168.25,
    "txUrl": "https://etherscan.io/tx/0x371e8945d08abf62e7c0257bb99cc5c84ea3c5a46ef017e09bae55dcaaeac028"
  },
  {
    "ts": "2026-07-04T23:55:02+00:00",
    "type": "inflow",
    "frxusd": 400.0,
    "asset": "USDC",
    "assetAmount": 400.0,
    "assetValueUSD": 400.0,
    "txUrl": "https://etherscan.io/tx/0x00df1b848557b82e9f28eac1615c98a7193ce87954b0304fe10b778475264d6a"
  },
  {
    "ts": "2026-07-04T23:55:01+00:00",
    "type": "inflow",
    "frxusd": 2000.0,
    "asset": "USDC",
    "assetAmount": 2000.0,
    "assetValueUSD": 2000.0,
    "txUrl": "https://etherscan.io/tx/0x00df1b848557b82e9f28eac1615c98a7193ce87954b0304fe10b778475264d6a"
  },
  {
    "ts": "2026-07-04T23:37:37+00:00",
    "type": "inflow",
    "frxusd": 8328.08,
    "asset": "USDC",
    "assetAmount": 8328.08,
    "assetValueUSD": 8328.08,
    "txUrl": "https://etherscan.io/tx/0x308b0e0aa1a2f6f16dc45a2e049e4dfa5585fe422210bb50bfb17b744adb7160"
  },
  {
    "ts": "2026-07-04T23:28:25+00:00",
    "type": "inflow",
    "frxusd": 6210.0,
    "asset": "USDC",
    "assetAmount": 6210.0,
    "assetValueUSD": 6210.0,
    "txUrl": "https://etherscan.io/tx/0x3017c81af0b63965cd495bfb164c6754277ab903aedfb84350377866a1c2fd81"
  },
  {
    "ts": "2026-07-04T23:15:52+00:00",
    "type": "outflow",
    "frxusd": 494.32,
    "asset": "USDC",
    "assetAmount": 494.32,
    "assetValueUSD": 494.32,
    "txUrl": "https://etherscan.io/tx/0xed3be3c277b740b4ef2077715cb8f5700258e0c6da9cf9860e78de9b2d8a16e9"
  },
  {
    "ts": "2026-07-04T23:15:51+00:00",
    "type": "outflow",
    "frxusd": 3802.9,
    "asset": "USTB",
    "assetAmount": 341.48,
    "assetValueUSD": 3802.52,
    "txUrl": "https://etherscan.io/tx/0x08985d5c627335445a13f3166a564d30b420bf4071594b31f99f594323b26969"
  },
  {
    "ts": "2026-07-04T23:15:50+00:00",
    "type": "outflow",
    "frxusd": 20979.43,
    "asset": "USTB",
    "assetAmount": 1883.85,
    "assetValueUSD": 20977.33,
    "txUrl": "https://etherscan.io/tx/0x3c53210ae38b04535e124d9f96ce83b5ffd0fac5fe53764e3a8e93f57993bc3e"
  },
  {
    "ts": "2026-07-04T23:15:49+00:00",
    "type": "outflow",
    "frxusd": 29780.6,
    "asset": "USTB",
    "assetAmount": 2674.16,
    "assetValueUSD": 29777.62,
    "txUrl": "https://etherscan.io/tx/0xa56fb161fcc4e04dc5a5c7bbfa919cba29386c0630cf7a5768aa09a30cd6c1cc"
  },
  {
    "ts": "2026-07-04T23:15:37+00:00",
    "type": "outflow",
    "frxusd": 28309.65,
    "asset": "USTB",
    "assetAmount": 2542.07,
    "assetValueUSD": 28306.82,
    "txUrl": "https://etherscan.io/tx/0xa0eeac7bd738705ed950a5cbc8d466decf10422d8d2a1e41f3ed75c50146226d"
  },
  {
    "ts": "2026-07-04T23:15:16+00:00",
    "type": "outflow",
    "frxusd": 1415.71,
    "asset": "USDC",
    "assetAmount": 1415.71,
    "assetValueUSD": 1415.71,
    "txUrl": "https://etherscan.io/tx/0x68694365dbf94fa78d53a20c4d181b09e25ff08f3de9e8b39710858cfb2fd0dc"
  },
  {
    "ts": "2026-07-04T23:15:14+00:00",
    "type": "outflow",
    "frxusd": 99882.68,
    "asset": "USDC",
    "assetAmount": 99882.68,
    "assetValueUSD": 99882.68,
    "txUrl": "https://etherscan.io/tx/0x9bb92f9d1ae4df7eb03e35a1c5a903b870a2302478cb772fcd26d2bc9daab11e"
  },
  {
    "ts": "2026-07-04T23:15:04+00:00",
    "type": "outflow",
    "frxusd": 989.91,
    "asset": "USDC",
    "assetAmount": 989.91,
    "assetValueUSD": 989.91,
    "txUrl": "https://etherscan.io/tx/0xe866342e32bafa2bc155b4a2389b44102b78e56999158fb8f2e4af259f1e45be"
  },
  {
    "ts": "2026-07-04T23:15:03+00:00",
    "type": "outflow",
    "frxusd": 405.85,
    "asset": "USDC",
    "assetAmount": 405.85,
    "assetValueUSD": 405.85,
    "txUrl": "https://etherscan.io/tx/0xdba9f949d6226703c747f10d99a4bc169af23c245b1e5eba2aea0d2f29032fff"
  },
  {
    "ts": "2026-07-04T23:15:02+00:00",
    "type": "outflow",
    "frxusd": 7863.77,
    "asset": "USDC",
    "assetAmount": 7863.77,
    "assetValueUSD": 7863.77,
    "txUrl": "https://etherscan.io/tx/0xdba9f949d6226703c747f10d99a4bc169af23c245b1e5eba2aea0d2f29032fff"
  },
  {
    "ts": "2026-07-04T23:15:01+00:00",
    "type": "outflow",
    "frxusd": 37277.48,
    "asset": "USDC",
    "assetAmount": 37277.48,
    "assetValueUSD": 37277.48,
    "txUrl": "https://etherscan.io/tx/0xdba9f949d6226703c747f10d99a4bc169af23c245b1e5eba2aea0d2f29032fff"
  },
  {
    "ts": "2026-07-04T22:49:38+00:00",
    "type": "inflow",
    "frxusd": 1599.51,
    "asset": "USDC",
    "assetAmount": 1599.51,
    "assetValueUSD": 1599.51,
    "txUrl": "https://etherscan.io/tx/0x385ec732591c648a03ddc60b86a268c9abdb48d31d71a1abbc4e69d7c8d06b4c"
  },
  {
    "ts": "2026-07-04T22:49:00+00:00",
    "type": "outflow",
    "frxusd": 992.07,
    "asset": "USDC",
    "assetAmount": 992.07,
    "assetValueUSD": 992.07,
    "txUrl": "https://etherscan.io/tx/0x7b462f5355f978d851d78eb10c1ecba928eddb86973d87ce7233d83fbde69465"
  },
  {
    "ts": "2026-07-04T22:47:49+00:00",
    "type": "inflow",
    "frxusd": 3.95,
    "asset": "USDC",
    "assetAmount": 3.95,
    "assetValueUSD": 3.95,
    "txUrl": "https://etherscan.io/tx/0xb19b4cafa6ac1965e8337b7fdf99fa5fea72e0ff90e2f9b8525f2092a5171c87"
  },
  {
    "ts": "2026-07-04T22:46:37+00:00",
    "type": "inflow",
    "frxusd": 1776.82,
    "asset": "USDC",
    "assetAmount": 1776.82,
    "assetValueUSD": 1776.82,
    "txUrl": "https://etherscan.io/tx/0x93b6cc729d2c1220edb0625f4cad994eda9f04353d7fa24744e3d4940d002a3b"
  },
  {
    "ts": "2026-07-04T22:28:27+00:00",
    "type": "outflow",
    "frxusd": 24.54,
    "asset": "USDC",
    "assetAmount": 24.54,
    "assetValueUSD": 24.54,
    "txUrl": "https://etherscan.io/tx/0x23c6beea046299f7b214221acfbcd0d86f60ae01970173dd9aadc7bbac19edf1"
  },
  {
    "ts": "2026-07-04T22:27:40+00:00",
    "type": "inflow",
    "frxusd": 4800.0,
    "asset": "USDC",
    "assetAmount": 4800.0,
    "assetValueUSD": 4800.0,
    "txUrl": "https://etherscan.io/tx/0xd416907d9e6c6ffed760596d629243d320689b5976e1bc1177dd4d16f7609bba"
  },
  {
    "ts": "2026-07-04T22:12:13+00:00",
    "type": "inflow",
    "frxusd": 198.7,
    "asset": "USDC",
    "assetAmount": 198.7,
    "assetValueUSD": 198.7,
    "txUrl": "https://etherscan.io/tx/0x77f796a9d59be0128b495126d9de75ab1113c7c97e9e97ed38a573524b223630"
  },
  {
    "ts": "2026-07-04T21:35:38+00:00",
    "type": "outflow",
    "frxusd": 894.72,
    "asset": "USDC",
    "assetAmount": 894.72,
    "assetValueUSD": 894.72,
    "txUrl": "https://etherscan.io/tx/0x44d0e3682f68df1c75e42cb870e3e4d64a2bb286ff2270d8d0ed37b47ffdebaf"
  },
  {
    "ts": "2026-07-04T21:33:01+00:00",
    "type": "outflow",
    "frxusd": 5250.0,
    "asset": "USDC",
    "assetAmount": 5250.0,
    "assetValueUSD": 5250.0,
    "txUrl": "https://etherscan.io/tx/0x47da1e7059fe8689239ba024e413049ae3308c22c3cecc281cd7c39064301d0d"
  },
  {
    "ts": "2026-07-04T21:23:50+00:00",
    "type": "inflow",
    "frxusd": 562.74,
    "asset": "USDC",
    "assetAmount": 562.74,
    "assetValueUSD": 562.74,
    "txUrl": "https://etherscan.io/tx/0x9ddace43d3bbd80b4c30445f66aff9451f37cbe3821e85e684787361ffb3ebdc"
  },
  {
    "ts": "2026-07-04T21:22:27+00:00",
    "type": "inflow",
    "frxusd": 200.0,
    "asset": "USDC",
    "assetAmount": 200.0,
    "assetValueUSD": 200.0,
    "txUrl": "https://etherscan.io/tx/0x3b5f31776a27830f5e2a69e0357b0b6ad4b451cc9dffd689bf93532e804eed63"
  },
  {
    "ts": "2026-07-04T21:20:02+00:00",
    "type": "inflow",
    "frxusd": 47.83,
    "asset": "USDC",
    "assetAmount": 47.83,
    "assetValueUSD": 47.83,
    "txUrl": "https://etherscan.io/tx/0x9aa404311eb5c339ab2417ed0f9125de6d76fe1ceb24aa26b62abfbb0b95627c"
  },
  {
    "ts": "2026-07-04T20:55:01+00:00",
    "type": "inflow",
    "frxusd": 377.57,
    "asset": "USDC",
    "assetAmount": 377.57,
    "assetValueUSD": 377.57,
    "txUrl": "https://etherscan.io/tx/0xa521c3358235e4dc3370ecc917497601096439438a41fbc698f79f371532ec12"
  },
  {
    "ts": "2026-07-04T20:50:37+00:00",
    "type": "inflow",
    "frxusd": 36400.0,
    "asset": "USDC",
    "assetAmount": 36400.0,
    "assetValueUSD": 36400.0,
    "txUrl": "https://etherscan.io/tx/0x9240f53baf1e3c00f5ee0dd1b559203279fcd64c3d4da9777518be8cfa1747d3"
  },
  {
    "ts": "2026-07-04T20:49:03+00:00",
    "type": "outflow",
    "frxusd": 996.08,
    "asset": "USDC",
    "assetAmount": 996.08,
    "assetValueUSD": 996.08,
    "txUrl": "https://etherscan.io/tx/0x0847c22342c5c4114f7eb31aac736279fe6628a7df13692dfd05a416676e1c8b"
  },
  {
    "ts": "2026-07-04T20:26:37+00:00",
    "type": "outflow",
    "frxusd": 71.37,
    "asset": "USDC",
    "assetAmount": 71.37,
    "assetValueUSD": 71.37,
    "txUrl": "https://etherscan.io/tx/0x36e8f1c691a2a64b6a436ed9346d9a0e9c1d048e0fa12b68a848bad34c3a5e30"
  },
  {
    "ts": "2026-07-04T20:20:27+00:00",
    "type": "outflow",
    "frxusd": 24675.42,
    "asset": "USDC",
    "assetAmount": 24675.42,
    "assetValueUSD": 24675.42,
    "txUrl": "https://etherscan.io/tx/0xc5c6b08bf441cd0e01d403aabac1fcc4e7e976cea874500f4748ee8cc326fda2"
  },
  {
    "ts": "2026-07-04T20:20:26+00:00",
    "type": "outflow",
    "frxusd": 68307.75,
    "asset": "USDC",
    "assetAmount": 68307.75,
    "assetValueUSD": 68307.75,
    "txUrl": "https://etherscan.io/tx/0xd22d2931419b9f68df2c0cc553754acca036479f9d1b20e553d3b54d6dbcc6b8"
  },
  {
    "ts": "2026-07-04T20:19:41+00:00",
    "type": "outflow",
    "frxusd": 21904.63,
    "asset": "USDC",
    "assetAmount": 21904.63,
    "assetValueUSD": 21904.63,
    "txUrl": "https://etherscan.io/tx/0x5b324e3503959dc93707dcb603cad061e0961169712f72b22780746746b0da26"
  },
  {
    "ts": "2026-07-04T20:19:40+00:00",
    "type": "outflow",
    "frxusd": 22961.16,
    "asset": "USDC",
    "assetAmount": 22961.16,
    "assetValueUSD": 22961.16,
    "txUrl": "https://etherscan.io/tx/0x080ac7b094b33eb2af5c5f9dbe2f9cfe2477933f61f8959cc412efc52a77e41a"
  },
  {
    "ts": "2026-07-04T20:19:02+00:00",
    "type": "outflow",
    "frxusd": 16962.08,
    "asset": "USDC",
    "assetAmount": 16962.08,
    "assetValueUSD": 16962.08,
    "txUrl": "https://etherscan.io/tx/0xaef2ccc039843eaa11f283be0c55b80a55e3a6489c4c3fe6d1e19048d324a72c"
  },
  {
    "ts": "2026-07-04T20:19:01+00:00",
    "type": "outflow",
    "frxusd": 31108.21,
    "asset": "USDC",
    "assetAmount": 31108.21,
    "assetValueUSD": 31108.21,
    "txUrl": "https://etherscan.io/tx/0x74bbc3c4c108301dcc01ab21dc10cc8ab80361a721ed777ed614127fef3892a5"
  },
  {
    "ts": "2026-07-04T20:18:50+00:00",
    "type": "outflow",
    "frxusd": 998.27,
    "asset": "USDC",
    "assetAmount": 998.27,
    "assetValueUSD": 998.27,
    "txUrl": "https://etherscan.io/tx/0x33e61b5d0e87c84724b3ce0d9e0f6bb862f91d3e0b45f4948328fa4aab3fac70"
  },
  {
    "ts": "2026-07-04T19:58:49+00:00",
    "type": "inflow",
    "frxusd": 1.99,
    "asset": "USDC",
    "assetAmount": 1.99,
    "assetValueUSD": 1.99,
    "txUrl": "https://etherscan.io/tx/0x9f3fd752fa15088703ba4fc2cbbaf25343a9b5f19c38d9b9862472f64ef748b1"
  },
  {
    "ts": "2026-07-04T19:58:14+00:00",
    "type": "outflow",
    "frxusd": 1000.46,
    "asset": "USDC",
    "assetAmount": 1000.46,
    "assetValueUSD": 1000.46,
    "txUrl": "https://etherscan.io/tx/0x6b8433af14861407a2654cfb76ed92babc8942569143e2cf24b2016be311ca28"
  },
  {
    "ts": "2026-07-04T19:57:49+00:00",
    "type": "inflow",
    "frxusd": 1760.0,
    "asset": "USDC",
    "assetAmount": 1760.0,
    "assetValueUSD": 1760.0,
    "txUrl": "https://etherscan.io/tx/0xd55682393260fa36a6b1f4c0247344fdbe243fdd8f0f91ec70b8c8489781ea6d"
  },
  {
    "ts": "2026-07-04T19:56:03+00:00",
    "type": "outflow",
    "frxusd": 998.8,
    "asset": "USDC",
    "assetAmount": 998.8,
    "assetValueUSD": 998.8,
    "txUrl": "https://etherscan.io/tx/0xbd458cdcb4485f1e09e89e451d41a9015eb4ebb0002fe448340a6481d3699a95"
  },
  {
    "ts": "2026-07-04T19:42:49+00:00",
    "type": "inflow",
    "frxusd": 6789.28,
    "asset": "USDC",
    "assetAmount": 6789.28,
    "assetValueUSD": 6789.28,
    "txUrl": "https://etherscan.io/tx/0xd4a5f8e756b88dbe9f11d3c0d97fe50e3a0abf75e9efcb34cfb84c46dc69847c"
  },
  {
    "ts": "2026-07-04T19:42:27+00:00",
    "type": "inflow",
    "frxusd": 7523.78,
    "asset": "USDC",
    "assetAmount": 7523.78,
    "assetValueUSD": 7523.78,
    "txUrl": "https://etherscan.io/tx/0x243acf6893fb89c7c1e480ecb866a1aff1369fa30e98002209290355462400ac"
  },
  {
    "ts": "2026-07-04T19:41:50+00:00",
    "type": "inflow",
    "frxusd": 6123.82,
    "asset": "USDC",
    "assetAmount": 6123.82,
    "assetValueUSD": 6123.82,
    "txUrl": "https://etherscan.io/tx/0x896e7dc448bd3054c08ccda0b30bce69e1040e777250f5c60a8dd263c922106a"
  },
  {
    "ts": "2026-07-04T19:41:49+00:00",
    "type": "inflow",
    "frxusd": 7027.37,
    "asset": "USDC",
    "assetAmount": 7027.37,
    "assetValueUSD": 7027.37,
    "txUrl": "https://etherscan.io/tx/0x555fe49b6ceefa5b9839a60d0efc47b4e1a428d1b64a3ab9dce752ae12368566"
  },
  {
    "ts": "2026-07-04T19:36:03+00:00",
    "type": "inflow",
    "frxusd": 6538.15,
    "asset": "USDC",
    "assetAmount": 6538.15,
    "assetValueUSD": 6538.15,
    "txUrl": "https://etherscan.io/tx/0x3ed8c084aed157acda5076d7136a20fd68223ae2b24a8c569c02e2861275c2f2"
  },
  {
    "ts": "2026-07-04T19:36:02+00:00",
    "type": "inflow",
    "frxusd": 6444.43,
    "asset": "USDC",
    "assetAmount": 6444.43,
    "assetValueUSD": 6444.43,
    "txUrl": "https://etherscan.io/tx/0x9da919ef072f5975ec5c76b40a00bb71d2c2bf02f58cb7010b58cb590e7bb493"
  },
  {
    "ts": "2026-07-04T19:36:02+00:00",
    "type": "inflow",
    "frxusd": 6729.76,
    "asset": "USDC",
    "assetAmount": 6729.76,
    "assetValueUSD": 6729.76,
    "txUrl": "https://etherscan.io/tx/0x7f601264962d1d49abe8a59dba4b5e355d20ec1a85bf2c236b42ff8a6368c8fb"
  },
  {
    "ts": "2026-07-04T19:36:01+00:00",
    "type": "inflow",
    "frxusd": 7050.41,
    "asset": "USDC",
    "assetAmount": 7050.41,
    "assetValueUSD": 7050.41,
    "txUrl": "https://etherscan.io/tx/0x9f0600604f54542f67fc6146c194b3ce0122f4e104f6f68e5c11200bf9197b40"
  },
  {
    "ts": "2026-07-04T19:34:51+00:00",
    "type": "inflow",
    "frxusd": 1992.76,
    "asset": "USDC",
    "assetAmount": 1992.76,
    "assetValueUSD": 1992.76,
    "txUrl": "https://etherscan.io/tx/0xb74cc9a6395ca401f85f68da4cde2a824bd022336113565c3c1b60381c786e38"
  },
  {
    "ts": "2026-07-04T19:30:25+00:00",
    "type": "outflow",
    "frxusd": 27.59,
    "asset": "USDC",
    "assetAmount": 27.59,
    "assetValueUSD": 27.59,
    "txUrl": "https://etherscan.io/tx/0xf89dd71e949323c64c91db944a3e65bbbc8cb32ad0ce297a99aa07b7587da41d"
  },
  {
    "ts": "2026-07-04T19:15:02+00:00",
    "type": "outflow",
    "frxusd": 2393.03,
    "asset": "USDC",
    "assetAmount": 2393.03,
    "assetValueUSD": 2393.03,
    "txUrl": "https://etherscan.io/tx/0xe89cee8e16210657a4b019472fff81f80381ac4b02c62fd6ca9e8e40a9e1a111"
  },
  {
    "ts": "2026-07-04T19:13:25+00:00",
    "type": "outflow",
    "frxusd": 1001.01,
    "asset": "USDC",
    "assetAmount": 1001.01,
    "assetValueUSD": 1001.01,
    "txUrl": "https://etherscan.io/tx/0xe7b433540b4fa7016cc6d614352d101ca17523738f0828eebd45cc019faa2dfc"
  },
  {
    "ts": "2026-07-04T18:49:50+00:00",
    "type": "outflow",
    "frxusd": 1003.21,
    "asset": "USDC",
    "assetAmount": 1003.21,
    "assetValueUSD": 1003.21,
    "txUrl": "https://etherscan.io/tx/0xdb3ba68856cffb04c2468943eee04366e44ed95288ea33256384e3c9897956d2"
  },
  {
    "ts": "2026-07-04T18:49:49+00:00",
    "type": "outflow",
    "frxusd": 1005.42,
    "asset": "USDC",
    "assetAmount": 1005.42,
    "assetValueUSD": 1005.42,
    "txUrl": "https://etherscan.io/tx/0xa0d732d94b5f14d0a5cfca313bfb9c40115172e6f60aed558ae17b6f768d7f1d"
  },
  {
    "ts": "2026-07-04T18:49:03+00:00",
    "type": "inflow",
    "frxusd": 68000.0,
    "asset": "USDC",
    "assetAmount": 68000.0,
    "assetValueUSD": 68000.0,
    "txUrl": "https://etherscan.io/tx/0x4ad746a45ff34aa1bb91590e53d52fda5ec2b6095e00d4e815a697444d972b27"
  },
  {
    "ts": "2026-07-04T18:47:01+00:00",
    "type": "inflow",
    "frxusd": 128000.0,
    "asset": "USDC",
    "assetAmount": 128000.0,
    "assetValueUSD": 128000.0,
    "txUrl": "https://etherscan.io/tx/0xdaa8891dc66d89803eb084a02deb29c4b4e05a7fb2d8fe13aac92ad98e853519"
  },
  {
    "ts": "2026-07-04T18:42:37+00:00",
    "type": "inflow",
    "frxusd": 46500.0,
    "asset": "USDC",
    "assetAmount": 46500.0,
    "assetValueUSD": 46500.0,
    "txUrl": "https://etherscan.io/tx/0x61a5983f44afb14d7be8923ab7b1ab40b82d0e3ff017222a530a81163f3340f7"
  },
  {
    "ts": "2026-07-04T18:42:13+00:00",
    "type": "inflow",
    "frxusd": 7800.0,
    "asset": "USDC",
    "assetAmount": 7800.0,
    "assetValueUSD": 7800.0,
    "txUrl": "https://etherscan.io/tx/0xfc47962685320ba9aa895b81a6bfeef829eee35d125c5ceb0859ab1397d82729"
  },
  {
    "ts": "2026-07-04T18:33:37+00:00",
    "type": "outflow",
    "frxusd": 3829.14,
    "asset": "USDC",
    "assetAmount": 3829.14,
    "assetValueUSD": 3829.14,
    "txUrl": "https://etherscan.io/tx/0xa240108b556cdc755dd6f104a37092af26a5aab6f6a6274608006ec3facaaf0f"
  },
  {
    "ts": "2026-07-04T18:33:25+00:00",
    "type": "inflow",
    "frxusd": 170.19,
    "asset": "USDC",
    "assetAmount": 170.19,
    "assetValueUSD": 170.19,
    "txUrl": "https://etherscan.io/tx/0x2958aac661db425bd10c374c87e7dead2dd3c5cc76bf40cd09239942ae6be869"
  },
  {
    "ts": "2026-07-04T18:32:49+00:00",
    "type": "outflow",
    "frxusd": 9971.39,
    "asset": "USDC",
    "assetAmount": 9971.39,
    "assetValueUSD": 9971.39,
    "txUrl": "https://etherscan.io/tx/0x262406e5f3ed4fae190c207fdd3de5770eb5a91e415d19e5186a663ed44ad238"
  },
  {
    "ts": "2026-07-04T18:31:52+00:00",
    "type": "outflow",
    "frxusd": 10006.87,
    "asset": "USDC",
    "assetAmount": 10006.87,
    "assetValueUSD": 10006.87,
    "txUrl": "https://etherscan.io/tx/0x1097769d041f110c6ddc0af90817ee5f9b5fededa61bccf643d4e566f444e2b0"
  },
  {
    "ts": "2026-07-04T18:31:51+00:00",
    "type": "outflow",
    "frxusd": 13072.25,
    "asset": "USDC",
    "assetAmount": 13072.25,
    "assetValueUSD": 13072.25,
    "txUrl": "https://etherscan.io/tx/0xff27af96ba4684eb3ace380fca09bc8a48656ea6b4f1166df8e455bce6c202c7"
  },
  {
    "ts": "2026-07-04T18:19:49+00:00",
    "type": "inflow",
    "frxusd": 14990.22,
    "asset": "USDC",
    "assetAmount": 14990.22,
    "assetValueUSD": 14990.22,
    "txUrl": "https://etherscan.io/tx/0x845316fd90a96fe8fcca724f8f361c379ad7168ed54af961dd608d6adf8bd725"
  },
  {
    "ts": "2026-07-04T18:17:51+00:00",
    "type": "inflow",
    "frxusd": 539.97,
    "asset": "USDC",
    "assetAmount": 539.97,
    "assetValueUSD": 539.97,
    "txUrl": "https://etherscan.io/tx/0xa55e69d22d04ddf862cef5f0935d028c472a9b7f9051ee951536c5102db58a74"
  },
  {
    "ts": "2026-07-04T18:16:49+00:00",
    "type": "outflow",
    "frxusd": 65246.03,
    "asset": "USDC",
    "assetAmount": 65246.03,
    "assetValueUSD": 65246.03,
    "txUrl": "https://etherscan.io/tx/0xf473a9972ad23389f664308be7a21aae5964dcb95546c8266a9b86846fef5953"
  },
  {
    "ts": "2026-07-04T18:14:25+00:00",
    "type": "inflow",
    "frxusd": 18090.07,
    "asset": "USDC",
    "assetAmount": 18090.07,
    "assetValueUSD": 18090.07,
    "txUrl": "https://etherscan.io/tx/0xdd9ece3fa4918dcd2d30fec4785dead4d1e2b39b16dc18cd8a44c2baddc39678"
  },
  {
    "ts": "2026-07-04T18:12:49+00:00",
    "type": "outflow",
    "frxusd": 44.76,
    "asset": "USDC",
    "assetAmount": 44.76,
    "assetValueUSD": 44.76,
    "txUrl": "https://etherscan.io/tx/0x9f4de6924ea6cd960ee7c894a3de22c383f016850fd442fd47933a667495a529"
  },
  {
    "ts": "2026-07-04T18:04:15+00:00",
    "type": "inflow",
    "frxusd": 10.0,
    "asset": "USDC",
    "assetAmount": 10.0,
    "assetValueUSD": 10.0,
    "txUrl": "https://etherscan.io/tx/0x9ac63ab6a07852222de912f8823e40eae98302abbbf9acb62537633820007d65"
  },
  {
    "ts": "2026-07-04T18:00:25+00:00",
    "type": "inflow",
    "frxusd": 4473.66,
    "asset": "USDC",
    "assetAmount": 4473.66,
    "assetValueUSD": 4473.66,
    "txUrl": "https://etherscan.io/tx/0x9f40426894bd3ede00922523467ffdd07dc668362a6d0a0db05299725dc34ec9"
  },
  {
    "ts": "2026-07-04T18:00:02+00:00",
    "type": "inflow",
    "frxusd": 1162.91,
    "asset": "USDC",
    "assetAmount": 1162.91,
    "assetValueUSD": 1162.91,
    "txUrl": "https://etherscan.io/tx/0x3c4be2e05d824dd654af13cde56921c9014259b03b7df9279ed46d76a827b52a"
  },
  {
    "ts": "2026-07-04T17:56:15+00:00",
    "type": "outflow",
    "frxusd": 4013.68,
    "asset": "USDC",
    "assetAmount": 4013.68,
    "assetValueUSD": 4013.68,
    "txUrl": "https://etherscan.io/tx/0xc71a6da4f8b358682e253b495ba188a7bc6855a9a6ac08081dbb92f4f934ebef"
  },
  {
    "ts": "2026-07-04T17:54:40+00:00",
    "type": "inflow",
    "frxusd": 190.3,
    "asset": "USDC",
    "assetAmount": 190.3,
    "assetValueUSD": 190.3,
    "txUrl": "https://etherscan.io/tx/0xf737178cfb9dd29122756fcf3503121bce800e82c8a97a4e9dd5b28f18ac61e1"
  },
  {
    "ts": "2026-07-04T17:54:40+00:00",
    "type": "inflow",
    "frxusd": 380.61,
    "asset": "USDC",
    "assetAmount": 380.61,
    "assetValueUSD": 380.61,
    "txUrl": "https://etherscan.io/tx/0xf737178cfb9dd29122756fcf3503121bce800e82c8a97a4e9dd5b28f18ac61e1"
  },
  {
    "ts": "2026-07-04T17:54:39+00:00",
    "type": "inflow",
    "frxusd": 16556.96,
    "asset": "USDC",
    "assetAmount": 16556.96,
    "assetValueUSD": 16556.96,
    "txUrl": "https://etherscan.io/tx/0xf737178cfb9dd29122756fcf3503121bce800e82c8a97a4e9dd5b28f18ac61e1"
  },
  {
    "ts": "2026-07-04T17:54:38+00:00",
    "type": "inflow",
    "frxusd": 1898.47,
    "asset": "USDC",
    "assetAmount": 1898.47,
    "assetValueUSD": 1898.47,
    "txUrl": "https://etherscan.io/tx/0xf737178cfb9dd29122756fcf3503121bce800e82c8a97a4e9dd5b28f18ac61e1"
  },
  {
    "ts": "2026-07-04T17:51:25+00:00",
    "type": "inflow",
    "frxusd": 1016.31,
    "asset": "USDC",
    "assetAmount": 1016.31,
    "assetValueUSD": 1016.31,
    "txUrl": "https://etherscan.io/tx/0x0f76ad145b80ecd24593fd9b209706cef3d2ccfa743ae9e9eb4a8a25a43c2eb1"
  },
  {
    "ts": "2026-07-04T17:45:26+00:00",
    "type": "outflow",
    "frxusd": 22800.0,
    "asset": "USDC",
    "assetAmount": 22800.0,
    "assetValueUSD": 22800.0,
    "txUrl": "https://etherscan.io/tx/0xb6ee1fa6f0cb22db162eb79c20702121afb15166dd3a6bcac80d260670c655d8"
  },
  {
    "ts": "2026-07-04T17:44:27+00:00",
    "type": "outflow",
    "frxusd": 30.01,
    "asset": "USDC",
    "assetAmount": 30.01,
    "assetValueUSD": 30.01,
    "txUrl": "https://etherscan.io/tx/0x86218b4ee4e2db03104692aadf33521862f582a85e11764d6c6cf52a94a15463"
  },
  {
    "ts": "2026-07-04T17:42:37+00:00",
    "type": "outflow",
    "frxusd": 60.02,
    "asset": "USDC",
    "assetAmount": 60.02,
    "assetValueUSD": 60.02,
    "txUrl": "https://etherscan.io/tx/0xa524ce6b1ae4ca73c6e0ba89b8d5f6bed342a63f0ed207c3c9fc4c5c3b168d8d"
  },
  {
    "ts": "2026-07-04T17:42:25+00:00",
    "type": "outflow",
    "frxusd": 3894.75,
    "asset": "USDC",
    "assetAmount": 3894.75,
    "assetValueUSD": 3894.75,
    "txUrl": "https://etherscan.io/tx/0xf53f5ad800293e33d252f9527680c5b2a70cb4c90021160971e570f3a2542ba4"
  },
  {
    "ts": "2026-07-04T17:42:25+00:00",
    "type": "inflow",
    "frxusd": 2000.0,
    "asset": "USDC",
    "assetAmount": 2000.0,
    "assetValueUSD": 2000.0,
    "txUrl": "https://etherscan.io/tx/0x45b0fed0af10e1b9e27f25db63baa8d89d6fef668ae8fe07ba503781ce39ab1d"
  },
  {
    "ts": "2026-07-04T17:41:51+00:00",
    "type": "outflow",
    "frxusd": 1853.49,
    "asset": "USDC",
    "assetAmount": 1853.49,
    "assetValueUSD": 1853.49,
    "txUrl": "https://etherscan.io/tx/0xb6d115a4e66330066d72cee9dd945ca10d371b76929b1ff5662408dff194eb0f"
  },
  {
    "ts": "2026-07-04T17:40:38+00:00",
    "type": "inflow",
    "frxusd": 800.0,
    "asset": "USDC",
    "assetAmount": 800.0,
    "assetValueUSD": 800.0,
    "txUrl": "https://etherscan.io/tx/0xa09ca4382d8a6f71faad65322c425d7e04e73752cf78ab29a0cee9a149d244a0"
  },
  {
    "ts": "2026-07-04T17:39:14+00:00",
    "type": "inflow",
    "frxusd": 1014.14,
    "asset": "USDC",
    "assetAmount": 1014.14,
    "assetValueUSD": 1014.14,
    "txUrl": "https://etherscan.io/tx/0x2c365caeeb01e2300ac7f014f9a110d8678edaf7859efaacea6bd04c0d3058dd"
  },
  {
    "ts": "2026-07-04T17:20:02+00:00",
    "type": "inflow",
    "frxusd": 417.05,
    "asset": "USDC",
    "assetAmount": 417.05,
    "assetValueUSD": 417.05,
    "txUrl": "https://etherscan.io/tx/0xe3beaa80ba5b9cf23994e5086af89e68ebc8c1708395f55e98facb4048115e82"
  },
  {
    "ts": "2026-07-04T17:19:50+00:00",
    "type": "outflow",
    "frxusd": 100.23,
    "asset": "USDC",
    "assetAmount": 100.23,
    "assetValueUSD": 100.23,
    "txUrl": "https://etherscan.io/tx/0xe41eb140f0fd8d8424d702fccdee5303fb9a6b8b84e4296c384976735d7d009b"
  },
  {
    "ts": "2026-07-04T17:19:49+00:00",
    "type": "inflow",
    "frxusd": 876.23,
    "asset": "USDC",
    "assetAmount": 876.23,
    "assetValueUSD": 876.23,
    "txUrl": "https://etherscan.io/tx/0xb63e894c69e54443815c8ffdfdc64c7f23bcd5b9135bfe1e6bc84326da93fc84"
  },
  {
    "ts": "2026-07-04T17:19:38+00:00",
    "type": "inflow",
    "frxusd": 824.3,
    "asset": "USDC",
    "assetAmount": 824.3,
    "assetValueUSD": 824.3,
    "txUrl": "https://etherscan.io/tx/0x376cc1907384cffe4ffc41d1268c36f4c7e15b4d0bebaf7aae6ede43e439e6d8"
  },
  {
    "ts": "2026-07-04T17:08:26+00:00",
    "type": "inflow",
    "frxusd": 1008.6,
    "asset": "USDC",
    "assetAmount": 1008.6,
    "assetValueUSD": 1008.6,
    "txUrl": "https://etherscan.io/tx/0x154aa92c62a46f5d3b34a41cf60072a1a26e9f7d74e8b40e0b88bb45f939ed84"
  },
  {
    "ts": "2026-07-04T17:08:01+00:00",
    "type": "inflow",
    "frxusd": 1003.52,
    "asset": "USDC",
    "assetAmount": 1003.52,
    "assetValueUSD": 1003.52,
    "txUrl": "https://etherscan.io/tx/0x53bdbfb1bfa44d7d2ddf33f81bbd4a057f70ddbc0e79028f5fb7a944d1f6b795"
  },
  {
    "ts": "2026-07-04T17:07:01+00:00",
    "type": "outflow",
    "frxusd": 100.23,
    "asset": "USDC",
    "assetAmount": 100.23,
    "assetValueUSD": 100.23,
    "txUrl": "https://etherscan.io/tx/0x4d823e9c82f8e110881f97233a0d707c69b6a91b0c8d1f120f3df64daf005983"
  },
  {
    "ts": "2026-07-04T17:06:51+00:00",
    "type": "inflow",
    "frxusd": 1001.57,
    "asset": "USDC",
    "assetAmount": 1001.57,
    "assetValueUSD": 1001.57,
    "txUrl": "https://etherscan.io/tx/0xea0c4012f19c24813585c9758807569827840e68f2e6ef8df3435f9e306d2f41"
  },
  {
    "ts": "2026-07-04T17:04:13+00:00",
    "type": "inflow",
    "frxusd": 919.88,
    "asset": "USDC",
    "assetAmount": 919.88,
    "assetValueUSD": 919.88,
    "txUrl": "https://etherscan.io/tx/0xf894f25b8b86c66d6618206b5e9864d477fe3747c6943af031861bb8455d7a0a"
  },
  {
    "ts": "2026-07-04T17:03:37+00:00",
    "type": "inflow",
    "frxusd": 2924.53,
    "asset": "USDC",
    "assetAmount": 2924.53,
    "assetValueUSD": 2924.53,
    "txUrl": "https://etherscan.io/tx/0x5269dc7875c8acb5f1b31ddc7b8a066fab99aa6c43192234e83803098ec46bf2"
  },
  {
    "ts": "2026-07-04T17:00:01+00:00",
    "type": "inflow",
    "frxusd": 998.0,
    "asset": "USDC",
    "assetAmount": 998.0,
    "assetValueUSD": 998.0,
    "txUrl": "https://etherscan.io/tx/0x9c3d56dcaa04f9d2eb20c771eeca676c2d4a32c91e77af0416bcee58fece4126"
  },
  {
    "ts": "2026-07-04T16:54:52+00:00",
    "type": "inflow",
    "frxusd": 250.0,
    "asset": "USDC",
    "assetAmount": 250.0,
    "assetValueUSD": 250.0,
    "txUrl": "https://etherscan.io/tx/0x250f428157743bc7f9da9bd7c02607c4a0e139de1225eca2481b080cf9ffdcfa"
  },
  {
    "ts": "2026-07-04T16:43:38+00:00",
    "type": "inflow",
    "frxusd": 998.65,
    "asset": "USDC",
    "assetAmount": 998.65,
    "assetValueUSD": 998.65,
    "txUrl": "https://etherscan.io/tx/0x99bea45b2e38f68e91beca74fabd536bf82c02b013bc308c82a57910cf43948f"
  },
  {
    "ts": "2026-07-04T16:43:37+00:00",
    "type": "inflow",
    "frxusd": 994.15,
    "asset": "USDC",
    "assetAmount": 994.15,
    "assetValueUSD": 994.15,
    "txUrl": "https://etherscan.io/tx/0x8ff90daf3992d9aac05f62d1ef01748dc88c76802b1edaffa2aae3635a69e132"
  },
  {
    "ts": "2026-07-04T16:32:01+00:00",
    "type": "inflow",
    "frxusd": 996.98,
    "asset": "USDC",
    "assetAmount": 996.98,
    "assetValueUSD": 996.98,
    "txUrl": "https://etherscan.io/tx/0x7387055a833ba8a165d2cc8d1a04bacaead64ca721841fcf9e07c8957e684b61"
  },
  {
    "ts": "2026-07-04T16:10:49+00:00",
    "type": "outflow",
    "frxusd": 17078.43,
    "asset": "USDC",
    "assetAmount": 17078.43,
    "assetValueUSD": 17078.43,
    "txUrl": "https://etherscan.io/tx/0xb5a238b9b2292d07aaadfbda88beec676f62212fa0e49253ce0fb6521c1480c5"
  },
  {
    "ts": "2026-07-04T16:08:25+00:00",
    "type": "outflow",
    "frxusd": 1.67,
    "asset": "USDC",
    "assetAmount": 1.67,
    "assetValueUSD": 1.67,
    "txUrl": "https://etherscan.io/tx/0x98b077c1f44f4876856f7d022649990df0979cd01ceb6ca4041270a6a9db74ca"
  },
  {
    "ts": "2026-07-04T16:04:01+00:00",
    "type": "outflow",
    "frxusd": 49.14,
    "asset": "USDC",
    "assetAmount": 49.14,
    "assetValueUSD": 49.14,
    "txUrl": "https://etherscan.io/tx/0x94062cf5446310a5e0faa1d4cb5a2271a86c13e6d258397335a1e99d7caf6dd2"
  },
  {
    "ts": "2026-07-04T16:02:01+00:00",
    "type": "outflow",
    "frxusd": 19097.86,
    "asset": "USDC",
    "assetAmount": 19097.86,
    "assetValueUSD": 19097.86,
    "txUrl": "https://etherscan.io/tx/0x39e5ebdfcb9057055f87610bde4ecde55e43a7b07aaccb784b88ecf06afc1420"
  },
  {
    "ts": "2026-07-04T16:01:26+00:00",
    "type": "outflow",
    "frxusd": 6675.05,
    "asset": "USDC",
    "assetAmount": 6675.05,
    "assetValueUSD": 6675.05,
    "txUrl": "https://etherscan.io/tx/0x47bbd51e5a3008fc653869ce827164dc7b462fc0ce388b05e3443aefb6ebe177"
  },
  {
    "ts": "2026-07-04T16:01:15+00:00",
    "type": "outflow",
    "frxusd": 10007.42,
    "asset": "USDC",
    "assetAmount": 10007.42,
    "assetValueUSD": 10007.42,
    "txUrl": "https://etherscan.io/tx/0xda79856a97e92ef63e6c9c782dff0af5d53c39504356dffbdd226bdbb681c8d1"
  },
  {
    "ts": "2026-07-04T16:01:14+00:00",
    "type": "outflow",
    "frxusd": 18690.13,
    "asset": "USDC",
    "assetAmount": 18690.13,
    "assetValueUSD": 18690.13,
    "txUrl": "https://etherscan.io/tx/0x2297bfd229c1e36435c8a2bc4bb316c2bd68d74b61a5fbe0e89aa9edd5caa1c6"
  },
  {
    "ts": "2026-07-04T16:01:13+00:00",
    "type": "outflow",
    "frxusd": 28006.76,
    "asset": "USDC",
    "assetAmount": 28006.76,
    "assetValueUSD": 28006.76,
    "txUrl": "https://etherscan.io/tx/0x3254d2b1f761faf77bc5f4278c838be89d56f8df4c31a89bf565b2dd1bf8ee5b"
  },
  {
    "ts": "2026-07-04T16:00:38+00:00",
    "type": "outflow",
    "frxusd": 20453.58,
    "asset": "USDC",
    "assetAmount": 20453.58,
    "assetValueUSD": 20453.58,
    "txUrl": "https://etherscan.io/tx/0x063a1f7decd021219eae04cffabaac50c5b6c87b82104ed7bc6cb620897bb275"
  },
  {
    "ts": "2026-07-04T16:00:37+00:00",
    "type": "outflow",
    "frxusd": 29457.0,
    "asset": "USDC",
    "assetAmount": 29457.0,
    "assetValueUSD": 29457.0,
    "txUrl": "https://etherscan.io/tx/0xdae3a59d69a2f5e761df022bcd1a59aa0cdd94853c7a6b227d09d7d2f94a8d0f"
  },
  {
    "ts": "2026-07-04T15:54:39+00:00",
    "type": "outflow",
    "frxusd": 20.0,
    "asset": "USDC",
    "assetAmount": 20.0,
    "assetValueUSD": 20.0,
    "txUrl": "https://etherscan.io/tx/0xb054ce75077e256a4bbf9972965b9b121c7133421f158cc01169c02f7d5482e0"
  },
  {
    "ts": "2026-07-04T15:38:26+00:00",
    "type": "outflow",
    "frxusd": 14255.79,
    "asset": "USDC",
    "assetAmount": 14255.79,
    "assetValueUSD": 14255.79,
    "txUrl": "https://etherscan.io/tx/0xd36d1f4e1b4b4bd277cbb810e5862799ffab283736925f5d3d8587c48251cdda"
  },
  {
    "ts": "2026-07-04T15:38:25+00:00",
    "type": "outflow",
    "frxusd": 14257.34,
    "asset": "USDC",
    "assetAmount": 14257.34,
    "assetValueUSD": 14257.34,
    "txUrl": "https://etherscan.io/tx/0xa52f2d948d1d4e4f8340c89d284c83326b71b73883f373bc2ab59bb7a72d573a"
  },
  {
    "ts": "2026-07-04T15:38:13+00:00",
    "type": "outflow",
    "frxusd": 29565.77,
    "asset": "USDC",
    "assetAmount": 29565.77,
    "assetValueUSD": 29565.77,
    "txUrl": "https://etherscan.io/tx/0x83e216968ad524cb969b05e72264488b309ca7b94936ceddd45b7aa300039583"
  },
  {
    "ts": "2026-07-04T15:38:04+00:00",
    "type": "outflow",
    "frxusd": 12517.9,
    "asset": "USDC",
    "assetAmount": 12517.9,
    "assetValueUSD": 12517.9,
    "txUrl": "https://etherscan.io/tx/0x29637312faac795f0c2c19c69f8b5182a9a50ee2be05d2c38cffc435eeb39a3a"
  },
  {
    "ts": "2026-07-04T15:32:14+00:00",
    "type": "outflow",
    "frxusd": 10006.73,
    "asset": "USDC",
    "assetAmount": 10006.73,
    "assetValueUSD": 10006.73,
    "txUrl": "https://etherscan.io/tx/0x41f38c26570d1866367cc27a6429e4043c75f585414547d117915c0d05b83adb"
  },
  {
    "ts": "2026-07-04T15:31:40+00:00",
    "type": "outflow",
    "frxusd": 9971.84,
    "asset": "USDC",
    "assetAmount": 9971.84,
    "assetValueUSD": 9971.84,
    "txUrl": "https://etherscan.io/tx/0x1ca14bf38ca6d37829051b2808a9bbd0a9ddb98ebc131984a23d64188d5d1b47"
  },
  {
    "ts": "2026-07-04T15:31:02+00:00",
    "type": "outflow",
    "frxusd": 31776.91,
    "asset": "USDC",
    "assetAmount": 31776.91,
    "assetValueUSD": 31776.91,
    "txUrl": "https://etherscan.io/tx/0xdcc009f96496bdff0780dd48658d961684bbe110d2787cdf79c5141a92528039"
  },
  {
    "ts": "2026-07-04T15:21:13+00:00",
    "type": "inflow",
    "frxusd": 990.11,
    "asset": "USDC",
    "assetAmount": 990.11,
    "assetValueUSD": 990.11,
    "txUrl": "https://etherscan.io/tx/0x0ea65b736d53b7b16283d4cd960ed0e1c1db3e41e8852bc4dd27ad69ea00ccd5"
  },
  {
    "ts": "2026-07-04T15:20:14+00:00",
    "type": "inflow",
    "frxusd": 464.1,
    "asset": "USDC",
    "assetAmount": 464.1,
    "assetValueUSD": 464.1,
    "txUrl": "https://etherscan.io/tx/0x0a1adad982414eca2fe91bf2b5d5da7ea7eb957970106a6a506581da67f65165"
  },
  {
    "ts": "2026-07-04T15:18:01+00:00",
    "type": "outflow",
    "frxusd": 11035.09,
    "asset": "USDC",
    "assetAmount": 11035.09,
    "assetValueUSD": 11035.09,
    "txUrl": "https://etherscan.io/tx/0x221708a1ce977444d644c50369fc0c049746940fbd15c778329f1739833efe7b"
  },
  {
    "ts": "2026-07-04T15:14:13+00:00",
    "type": "inflow",
    "frxusd": 30005.36,
    "asset": "USDC",
    "assetAmount": 30005.36,
    "assetValueUSD": 30005.36,
    "txUrl": "https://etherscan.io/tx/0x009573924d1f5da7ab4613a418940fd7bd07b95e45746ba619878eece9998b0c"
  },
  {
    "ts": "2026-07-04T15:10:27+00:00",
    "type": "inflow",
    "frxusd": 205399.51,
    "asset": "USDC",
    "assetAmount": 205399.51,
    "assetValueUSD": 205399.51,
    "txUrl": "https://etherscan.io/tx/0x81053f317d1fe37c03fffd9980ffae5846b76a7b0cab3e9de91f40011622dd7e"
  },
  {
    "ts": "2026-07-04T15:10:17+00:00",
    "type": "inflow",
    "frxusd": 991.22,
    "asset": "USDC",
    "assetAmount": 991.22,
    "assetValueUSD": 991.22,
    "txUrl": "https://etherscan.io/tx/0x384603fb9a9b97cda5ef558c5181682c8b83641d49b65d4bd074b2d6a29ff6ec"
  },
  {
    "ts": "2026-07-04T15:10:16+00:00",
    "type": "inflow",
    "frxusd": 986.34,
    "asset": "USDC",
    "assetAmount": 986.34,
    "assetValueUSD": 986.34,
    "txUrl": "https://etherscan.io/tx/0x8cd89b7cc3d7b24aee23badea6b4c9eba57b7f53935840a5e8fd8fca1d4bc9ff"
  },
  {
    "ts": "2026-07-04T15:10:15+00:00",
    "type": "inflow",
    "frxusd": 12029.05,
    "asset": "USDC",
    "assetAmount": 12029.05,
    "assetValueUSD": 12029.05,
    "txUrl": "https://etherscan.io/tx/0x320ae312b96ee3ce1ee34a67e83636cb49c0604b7a284aae743dbb8c4af54470"
  },
  {
    "ts": "2026-07-04T15:10:14+00:00",
    "type": "inflow",
    "frxusd": 90509.0,
    "asset": "USDC",
    "assetAmount": 90509.0,
    "assetValueUSD": 90509.0,
    "txUrl": "https://etherscan.io/tx/0x320ae312b96ee3ce1ee34a67e83636cb49c0604b7a284aae743dbb8c4af54470"
  },
  {
    "ts": "2026-07-04T14:49:01+00:00",
    "type": "inflow",
    "frxusd": 72.09,
    "asset": "USDC",
    "assetAmount": 72.09,
    "assetValueUSD": 72.09,
    "txUrl": "https://etherscan.io/tx/0x6c1fba236f95c782f87add21bffc1f12f6797ae28cebdf31e4169b5a5ca190c6"
  },
  {
    "ts": "2026-07-04T14:43:39+00:00",
    "type": "inflow",
    "frxusd": 1.76,
    "asset": "USDC",
    "assetAmount": 1.76,
    "assetValueUSD": 1.76,
    "txUrl": "https://etherscan.io/tx/0xedeec6f56b7e70a5f313603df520c927dfe3d4e663638d22a81ded7fe75c4e94"
  },
  {
    "ts": "2026-07-04T14:38:25+00:00",
    "type": "outflow",
    "frxusd": 1509.11,
    "asset": "USTB",
    "assetAmount": 135.51,
    "assetValueUSD": 1508.96,
    "txUrl": "https://etherscan.io/tx/0xf0de93a994a8b08088cdb349f95db02e29f590e248777ae8277db842c0f2ba6d"
  },
  {
    "ts": "2026-07-04T14:30:15+00:00",
    "type": "outflow",
    "frxusd": 70.0,
    "asset": "USDC",
    "assetAmount": 70.0,
    "assetValueUSD": 70.0,
    "txUrl": "https://etherscan.io/tx/0x65c287b777de83c9447d451b8f3f0f6d726187bf243e7095419e1edec982903d"
  },
  {
    "ts": "2026-07-04T14:28:50+00:00",
    "type": "inflow",
    "frxusd": 21.58,
    "asset": "USDC",
    "assetAmount": 21.58,
    "assetValueUSD": 21.58,
    "txUrl": "https://etherscan.io/tx/0xc232c0d5f952442c8fc2a3877f6346dac9eceb775815f5d366c76369fc448e7d"
  },
  {
    "ts": "2026-07-04T13:29:51+00:00",
    "type": "outflow",
    "frxusd": 102.64,
    "asset": "USDC",
    "assetAmount": 102.64,
    "assetValueUSD": 102.64,
    "txUrl": "https://etherscan.io/tx/0x032279b4bd99b0f159937fcd970e50d751d73eecf3695d85ec3060e1c0764bdb"
  },
  {
    "ts": "2026-07-04T12:25:01+00:00",
    "type": "inflow",
    "frxusd": 96.77,
    "asset": "USDC",
    "assetAmount": 96.77,
    "assetValueUSD": 96.77,
    "txUrl": "https://etherscan.io/tx/0x371117cd31cf0b84fed9727f9b9a4099c5a77025fcdcc26d10bea0296aa30dc6"
  },
  {
    "ts": "2026-07-04T12:20:01+00:00",
    "type": "outflow",
    "frxusd": 4729.78,
    "asset": "USDC",
    "assetAmount": 4729.78,
    "assetValueUSD": 4729.78,
    "txUrl": "https://etherscan.io/tx/0x9fb93ea165be1b1f9f5db69ac13f1cd56e9bb05a39d36a87547dff3ed4377eac"
  },
  {
    "ts": "2026-07-04T12:19:49+00:00",
    "type": "inflow",
    "frxusd": 1825.6,
    "asset": "USDC",
    "assetAmount": 1825.6,
    "assetValueUSD": 1825.6,
    "txUrl": "https://etherscan.io/tx/0x5e63d5d99a91332d7e7d26570dbe884bd0e091e04b8b973e1529f48be112840e"
  },
  {
    "ts": "2026-07-04T12:15:38+00:00",
    "type": "inflow",
    "frxusd": 984.46,
    "asset": "USDC",
    "assetAmount": 984.46,
    "assetValueUSD": 984.46,
    "txUrl": "https://etherscan.io/tx/0x3be21f09fcf7055398ef7ad918a3fa30a6f4013ee4e5b9d257d85598a071974e"
  },
  {
    "ts": "2026-07-04T12:12:25+00:00",
    "type": "inflow",
    "frxusd": 1000.0,
    "asset": "USDC",
    "assetAmount": 1000.0,
    "assetValueUSD": 1000.0,
    "txUrl": "https://etherscan.io/tx/0x82f6f20b8410cbf06780e1229348d8859f9e1fd61c730922940e93d31f2518fa"
  },
  {
    "ts": "2026-07-04T12:07:49+00:00",
    "type": "inflow",
    "frxusd": 700.0,
    "asset": "USDC",
    "assetAmount": 700.0,
    "assetValueUSD": 700.0,
    "txUrl": "https://etherscan.io/tx/0x4b0b39f496f141bfa765b5c41a6b970b3273440678f7450d9f6e74a9a2aefc59"
  },
  {
    "ts": "2026-07-04T11:56:14+00:00",
    "type": "outflow",
    "frxusd": 4000.28,
    "asset": "USDC",
    "assetAmount": 4000.28,
    "assetValueUSD": 4000.28,
    "txUrl": "https://etherscan.io/tx/0x4d8c2a9cb4785fa751a306fa4a23204239b7e8b06eb708d0699cb7bfd7cff76e"
  },
  {
    "ts": "2026-07-04T11:56:13+00:00",
    "type": "outflow",
    "frxusd": 41951.55,
    "asset": "USDC",
    "assetAmount": 41951.55,
    "assetValueUSD": 41951.55,
    "txUrl": "https://etherscan.io/tx/0x4d8c2a9cb4785fa751a306fa4a23204239b7e8b06eb708d0699cb7bfd7cff76e"
  },
  {
    "ts": "2026-07-04T11:56:02+00:00",
    "type": "inflow",
    "frxusd": 45178.86,
    "asset": "USDC",
    "assetAmount": 45178.86,
    "assetValueUSD": 45178.86,
    "txUrl": "https://etherscan.io/tx/0x4bfcd52b6682b12e1843d3a1a0abf8c010fc37a416b5807545f3da155fff6944"
  },
  {
    "ts": "2026-07-04T11:54:25+00:00",
    "type": "inflow",
    "frxusd": 1000.0,
    "asset": "USDC",
    "assetAmount": 1000.0,
    "assetValueUSD": 1000.0,
    "txUrl": "https://etherscan.io/tx/0xef8bebcb78d49b004ffe99abb7148b89ce68e920a9dfe150715181a5fffedc49"
  },
  {
    "ts": "2026-07-04T11:16:25+00:00",
    "type": "outflow",
    "frxusd": 123.03,
    "asset": "USDC",
    "assetAmount": 123.03,
    "assetValueUSD": 123.03,
    "txUrl": "https://etherscan.io/tx/0xdd73533b6f23a02c15cd98b0f746878f1e8e4b98312b0ca76b254e146f162a74"
  },
  {
    "ts": "2026-07-04T10:23:13+00:00",
    "type": "inflow",
    "frxusd": 159.94,
    "asset": "USDC",
    "assetAmount": 159.94,
    "assetValueUSD": 159.94,
    "txUrl": "https://etherscan.io/tx/0x48f5be30e05c1b7b849fd71c0bf7f49bfface773cb0e4930f07d348343be3b60"
  },
  {
    "ts": "2026-07-04T10:02:37+00:00",
    "type": "inflow",
    "frxusd": 11.35,
    "asset": "USDC",
    "assetAmount": 11.35,
    "assetValueUSD": 11.35,
    "txUrl": "https://etherscan.io/tx/0x262884baba002568140c022c45f6e4697da2c79361fd53fdb1ad8bd1c95df0d1"
  },
  {
    "ts": "2026-07-04T09:40:13+00:00",
    "type": "outflow",
    "frxusd": 1233.41,
    "asset": "USDC",
    "assetAmount": 1233.41,
    "assetValueUSD": 1233.41,
    "txUrl": "https://etherscan.io/tx/0x98e607d9b198a1ffef7ef9d3ba02c1981987d2da2f9ca2050c40a40ca3688d4a"
  }
]